<?xml version="1.0" encoding="utf-8"?>
<Exports>
  <Panels>
    <PanelSettings>
      <SortPriority>0</SortPriority>
      <IsChecked>false</IsChecked>
      <IsExpanded>true</IsExpanded>
      <Enabled>false</Enabled>
      <PanelName>シナジースキル効果時間表示</PanelName>
      <ID>682207e0-c8bb-40ee-9f5a-687041c092fd</ID>
      <Left>1328</Left>
      <Locked>false</Locked>
      <Top>583</Top>
      <Margin>-7</Margin>
      <Horizontal>true</Horizontal>
      <SortOrder>SortRecastTimeASC</SortOrder>
      <EnabledAdvancedLayout>false</EnabledAdvancedLayout>
      <Width>450</Width>
      <Height>80</Height>
      <GridPadding>0 0 0 0</GridPadding>
      <GridVerticalAlignment>Top</GridVerticalAlignment>
      <GridHorizontalAlignment>Left</GridHorizontalAlignment>
      <IsStackLayout>false</IsStackLayout>
      <StackPanelOrientation>Horizontal</StackPanelOrientation>
      <FixedPositionSpell>false</FixedPositionSpell>
      <BackgroundColor>
        <A>1</A>
        <R>0</R>
        <G>0</G>
        <B>0</B>
        <ScA>0.003921569</ScA>
        <ScR>0</ScR>
        <ScG>0</ScG>
        <ScB>0</ScB>
      </BackgroundColor>
    </PanelSettings>
  </Panels>
  <Spells>
    <SpellTimer>
      <SortPriority>0</SortPriority>
      <IsChecked>false</IsChecked>
      <IsExpanded>false</IsExpanded>
      <Enabled>true</Enabled>
      <IsCircleStyle>true</IsCircleStyle>
      <TitleVerticalAlignmentInCircle>Center</TitleVerticalAlignmentInCircle>
      <Left>0</Left>
      <Top>0</Top>
      <ID>236</ID>
      <Guid>985d9866-9570-4f57-a34d-504f65b6f6ea</Guid>
      <PanelID>682207e0-c8bb-40ee-9f5a-687041c092fd</PanelID>
      <Panel>シナジースキル効果時間表示</Panel>
      <SpellTitle>挑発</SpellTitle>
      <RegexEnabled>true</RegexEnabled>
      <Keyword>^00:&lt;id4&gt;:&lt;mex&gt;の「挑発」$</Keyword>
      <KeywordForExtend1 />
      <KeywordForExtend2 />
      <RecastTime>30</RecastTime>
      <DelayToShow>0</DelayToShow>
      <RecastTimeExtending1>0</RecastTimeExtending1>
      <RecastTimeExtending2>0</RecastTimeExtending2>
      <RecastTimeExtending3>0</RecastTimeExtending3>
      <OverlapRecastTime>true</OverlapRecastTime>
      <IsNotResetBarOnExtended>false</IsNotResetBarOnExtended>
      <ProgressBarVisible>true</ProgressBarVisible>
      <Font FontFamily="Impact" Size="14" Stretch="Condensed" Style="Normal" Weight="Normal" />
      <FontColor>#FFFFFF</FontColor>
      <FontOutlineColor>#696969</FontOutlineColor>
      <WarningTime>0</WarningTime>
      <ChangeFontColorsWhenWarning>false</ChangeFontColorsWhenWarning>
      <WarningFontColor>#FFFFFF</WarningFontColor>
      <WarningFontOutlineColor>#FF4500</WarningFontOutlineColor>
      <ChangeFontColorWhenContainsMe>false</ChangeFontColorWhenContainsMe>
      <BarWidth>35</BarWidth>
      <BarHeight>3</BarHeight>
      <BarColor>#FFFFFF</BarColor>
      <BarOutlineColor>#191970</BarOutlineColor>
      <BarBlurRadius>0</BarBlurRadius>
      <BackgroundColor>#FFFFFF</BackgroundColor>
      <BackgroundAlpha>0</BackgroundAlpha>
      <DisplayNo>0</DisplayNo>
      <DontHide>false</DontHide>
      <IsHideInNotCombat>false</IsHideInNotCombat>
      <ExtendBeyondOriginalRecastTime>false</ExtendBeyondOriginalRecastTime>
      <HideSpellName>true</HideSpellName>
      <HideCounter>false</HideCounter>
      <IsCounterToCenter>false</IsCounterToCenter>
      <IsReverse>false</IsReverse>
      <MatchDateTime>0001-01-01T00:00:00</MatchDateTime>
      <UseHotbarRecastTime>false</UseHotbarRecastTime>
      <HotbarName />
      <ReduceIconBrightness>true</ReduceIconBrightness>
      <SpellIcon>7533_挑発.png</SpellIcon>
      <SpellIconSize>29</SpellIconSize>
      <IsNotResetAtWipeout>false</IsNotResetAtWipeout>
      <TimeupHide>false</TimeupHide>
      <ToInstance>false</ToInstance>
      <UpperLimitOfExtension>0</UpperLimitOfExtension>
      <BlinkTime>5</BlinkTime>
      <BlinkIcon>false</BlinkIcon>
      <BlinkBar>true</BlinkBar>
      <JobFilter>1,3,19,21,32,37</JobFilter>
      <PartyJobFilter />
      <PartyCompositionFilter />
      <ZoneFilter />
      <TimersMustRunningForStart />
      <TimersMustStoppingForStart />
      <ExpressionFilter>
        <expression />
        <expression />
        <expression />
        <expression />
      </ExpressionFilter>
      <IsSequentialTTS>false</IsSequentialTTS>
      <MatchTextToSpeak />
      <MatchAdvancedConfig>
        <IsEnabled>false</IsEnabled>
        <ToMainDevice>true</ToMainDevice>
        <ToSubDevice>false</ToSubDevice>
        <ToDicordTextChat>false</ToDicordTextChat>
        <Palette>Default</Palette>
      </MatchAdvancedConfig>
      <OverTime>0</OverTime>
      <OverTextToSpeak />
      <OverAdvancedConfig>
        <IsEnabled>false</IsEnabled>
        <ToMainDevice>true</ToMainDevice>
        <ToSubDevice>false</ToSubDevice>
        <ToDicordTextChat>false</ToDicordTextChat>
        <Palette>Default</Palette>
      </OverAdvancedConfig>
      <BeforeTime>3</BeforeTime>
      <BeforeTextToSpeak>挑発3秒前</BeforeTextToSpeak>
      <BeforeAdvancedConfig>
        <IsEnabled>false</IsEnabled>
        <ToMainDevice>true</ToMainDevice>
        <ToSubDevice>false</ToSubDevice>
        <ToDicordTextChat>false</ToDicordTextChat>
        <Palette>Default</Palette>
      </BeforeAdvancedConfig>
      <TimeupTextToSpeak />
      <TimeupAdvancedConfig>
        <IsEnabled>false</IsEnabled>
        <ToMainDevice>true</ToMainDevice>
        <ToSubDevice>false</ToSubDevice>
        <ToDicordTextChat>false</ToDicordTextChat>
        <Palette>Default</Palette>
      </TimeupAdvancedConfig>
      <MatchSound />
      <OverSound />
      <BeforeSound />
      <TimeupSound />
    </SpellTimer>
    <SpellTimer>
      <SortPriority>0</SortPriority>
      <IsChecked>false</IsChecked>
      <IsExpanded>false</IsExpanded>
      <Enabled>true</Enabled>
      <IsCircleStyle>true</IsCircleStyle>
      <TitleVerticalAlignmentInCircle>Center</TitleVerticalAlignmentInCircle>
      <Left>0</Left>
      <Top>0</Top>
      <ID>1</ID>
      <Guid>bff402e5-2b54-4dc9-8c98-58e492d8e086</Guid>
      <PanelID>682207e0-c8bb-40ee-9f5a-687041c092fd</PanelID>
      <Panel>シナジースキル効果時間表示</Panel>
      <SpellTitle>ランパート</SpellTitle>
      <RegexEnabled>true</RegexEnabled>
      <Keyword>^00:&lt;id4&gt;:&lt;mex&gt;の「ランパート」$</Keyword>
      <RecastTime>90</RecastTime>
      <DelayToShow>0</DelayToShow>
      <RecastTimeExtending1>0</RecastTimeExtending1>
      <RecastTimeExtending2>0</RecastTimeExtending2>
      <RecastTimeExtending3>0</RecastTimeExtending3>
      <OverlapRecastTime>true</OverlapRecastTime>
      <IsNotResetBarOnExtended>false</IsNotResetBarOnExtended>
      <ProgressBarVisible>true</ProgressBarVisible>
      <Font FontFamily="Impact" Size="14" Stretch="Condensed" Style="Normal" Weight="Normal" />
      <FontColor>#FFFFFF</FontColor>
      <FontOutlineColor>#000080</FontOutlineColor>
      <WarningTime>0</WarningTime>
      <ChangeFontColorsWhenWarning>false</ChangeFontColorsWhenWarning>
      <WarningFontColor>#FFFFFF</WarningFontColor>
      <WarningFontOutlineColor>#FF0000</WarningFontOutlineColor>
      <ChangeFontColorWhenContainsMe>true</ChangeFontColorWhenContainsMe>
      <BarWidth>35</BarWidth>
      <BarHeight>3</BarHeight>
      <BarColor>#FFFFFF</BarColor>
      <BarOutlineColor>#000080</BarOutlineColor>
      <BarBlurRadius>0</BarBlurRadius>
      <BackgroundColor>#000000</BackgroundColor>
      <BackgroundAlpha>0</BackgroundAlpha>
      <DisplayNo>1</DisplayNo>
      <DontHide>false</DontHide>
      <IsHideInNotCombat>false</IsHideInNotCombat>
      <ExtendBeyondOriginalRecastTime>false</ExtendBeyondOriginalRecastTime>
      <HideSpellName>true</HideSpellName>
      <HideCounter>false</HideCounter>
      <IsCounterToCenter>false</IsCounterToCenter>
      <IsReverse>false</IsReverse>
      <MatchDateTime>0001-01-01T00:00:00</MatchDateTime>
      <UseHotbarRecastTime>false</UseHotbarRecastTime>
      <HotbarName />
      <ReduceIconBrightness>true</ReduceIconBrightness>
      <SpellIcon>7531_ランパート.png</SpellIcon>
      <SpellIconSize>29</SpellIconSize>
      <IsNotResetAtWipeout>false</IsNotResetAtWipeout>
      <TimeupHide>false</TimeupHide>
      <ToInstance>false</ToInstance>
      <UpperLimitOfExtension>0</UpperLimitOfExtension>
      <BlinkTime>5</BlinkTime>
      <BlinkIcon>false</BlinkIcon>
      <BlinkBar>true</BlinkBar>
      <JobFilter>1,3,19,21,32,37</JobFilter>
      <PartyJobFilter />
      <PartyCompositionFilter />
      <ZoneFilter />
      <TimersMustRunningForStart />
      <TimersMustStoppingForStart />
      <ExpressionFilter>
        <expression />
        <expression />
        <expression />
        <expression />
      </ExpressionFilter>
      <IsSequentialTTS>false</IsSequentialTTS>
      <MatchTextToSpeak />
      <MatchAdvancedConfig>
        <IsEnabled>false</IsEnabled>
        <ToMainDevice>true</ToMainDevice>
        <ToSubDevice>false</ToSubDevice>
        <ToDicordTextChat>false</ToDicordTextChat>
        <Palette>Default</Palette>
      </MatchAdvancedConfig>
      <OverTime>0</OverTime>
      <OverTextToSpeak />
      <OverAdvancedConfig>
        <IsEnabled>false</IsEnabled>
        <ToMainDevice>true</ToMainDevice>
        <ToSubDevice>false</ToSubDevice>
        <ToDicordTextChat>false</ToDicordTextChat>
        <Palette>Default</Palette>
      </OverAdvancedConfig>
      <BeforeTime>3</BeforeTime>
      <BeforeTextToSpeak>ランパ3秒前</BeforeTextToSpeak>
      <BeforeAdvancedConfig>
        <IsEnabled>false</IsEnabled>
        <ToMainDevice>true</ToMainDevice>
        <ToSubDevice>false</ToSubDevice>
        <ToDicordTextChat>false</ToDicordTextChat>
        <Palette>Default</Palette>
      </BeforeAdvancedConfig>
      <TimeupTextToSpeak />
      <TimeupAdvancedConfig>
        <IsEnabled>false</IsEnabled>
        <ToMainDevice>true</ToMainDevice>
        <ToSubDevice>false</ToSubDevice>
        <ToDicordTextChat>false</ToDicordTextChat>
        <Palette>Default</Palette>
      </TimeupAdvancedConfig>
      <MatchSound />
      <OverSound />
      <BeforeSound />
      <TimeupSound />
    </SpellTimer>
    <SpellTimer>
      <SortPriority>0</SortPriority>
      <IsChecked>false</IsChecked>
      <IsExpanded>false</IsExpanded>
      <Enabled>true</Enabled>
      <IsCircleStyle>true</IsCircleStyle>
      <TitleVerticalAlignmentInCircle>Center</TitleVerticalAlignmentInCircle>
      <Left>0</Left>
      <Top>0</Top>
      <ID>234</ID>
      <Guid>fa9b476a-9516-46ab-9ebe-46aabb9abc49</Guid>
      <PanelID>682207e0-c8bb-40ee-9f5a-687041c092fd</PanelID>
      <Panel>シナジースキル効果時間表示</Panel>
      <SpellTitle>リプライザル</SpellTitle>
      <RegexEnabled>true</RegexEnabled>
      <Keyword>^00:&lt;id4&gt;:&lt;mex&gt;の「リプライザル」$</Keyword>
      <KeywordForExtend1 />
      <KeywordForExtend2 />
      <RecastTime>60</RecastTime>
      <DelayToShow>0</DelayToShow>
      <RecastTimeExtending1>0</RecastTimeExtending1>
      <RecastTimeExtending2>0</RecastTimeExtending2>
      <RecastTimeExtending3>0</RecastTimeExtending3>
      <OverlapRecastTime>true</OverlapRecastTime>
      <IsNotResetBarOnExtended>false</IsNotResetBarOnExtended>
      <ProgressBarVisible>true</ProgressBarVisible>
      <Font FontFamily="Impact" Size="14" Stretch="Condensed" Style="Normal" Weight="Normal" />
      <FontColor>#FFFFFF</FontColor>
      <FontOutlineColor>#696969</FontOutlineColor>
      <WarningTime>0</WarningTime>
      <ChangeFontColorsWhenWarning>false</ChangeFontColorsWhenWarning>
      <WarningFontColor>#FFFFFF</WarningFontColor>
      <WarningFontOutlineColor>#FF4500</WarningFontOutlineColor>
      <ChangeFontColorWhenContainsMe>true</ChangeFontColorWhenContainsMe>
      <BarWidth>35</BarWidth>
      <BarHeight>3</BarHeight>
      <BarColor>#FFFFFF</BarColor>
      <BarOutlineColor>#191970</BarOutlineColor>
      <BarBlurRadius>0</BarBlurRadius>
      <BackgroundColor>#FFFFFF</BackgroundColor>
      <BackgroundAlpha>0</BackgroundAlpha>
      <DisplayNo>2</DisplayNo>
      <DontHide>false</DontHide>
      <IsHideInNotCombat>false</IsHideInNotCombat>
      <ExtendBeyondOriginalRecastTime>false</ExtendBeyondOriginalRecastTime>
      <HideSpellName>true</HideSpellName>
      <HideCounter>false</HideCounter>
      <IsCounterToCenter>false</IsCounterToCenter>
      <IsReverse>false</IsReverse>
      <MatchDateTime>0001-01-01T00:00:00</MatchDateTime>
      <UseHotbarRecastTime>false</UseHotbarRecastTime>
      <HotbarName />
      <ReduceIconBrightness>true</ReduceIconBrightness>
      <SpellIcon>7535_リプライザル.png</SpellIcon>
      <SpellIconSize>29</SpellIconSize>
      <IsNotResetAtWipeout>false</IsNotResetAtWipeout>
      <TimeupHide>false</TimeupHide>
      <ToInstance>false</ToInstance>
      <UpperLimitOfExtension>0</UpperLimitOfExtension>
      <BlinkTime>5</BlinkTime>
      <BlinkIcon>false</BlinkIcon>
      <BlinkBar>true</BlinkBar>
      <JobFilter>1,3,19,21,32,37</JobFilter>
      <PartyJobFilter />
      <PartyCompositionFilter />
      <ZoneFilter />
      <TimersMustRunningForStart />
      <TimersMustStoppingForStart />
      <ExpressionFilter>
        <expression />
        <expression />
        <expression />
        <expression />
      </ExpressionFilter>
      <IsSequentialTTS>false</IsSequentialTTS>
      <MatchTextToSpeak />
      <MatchAdvancedConfig>
        <IsEnabled>false</IsEnabled>
        <ToMainDevice>true</ToMainDevice>
        <ToSubDevice>false</ToSubDevice>
        <ToDicordTextChat>false</ToDicordTextChat>
        <Palette>Default</Palette>
      </MatchAdvancedConfig>
      <OverTime>0</OverTime>
      <OverTextToSpeak />
      <OverAdvancedConfig>
        <IsEnabled>false</IsEnabled>
        <ToMainDevice>true</ToMainDevice>
        <ToSubDevice>false</ToSubDevice>
        <ToDicordTextChat>false</ToDicordTextChat>
        <Palette>Default</Palette>
      </OverAdvancedConfig>
      <BeforeTime>3</BeforeTime>
      <BeforeTextToSpeak>リプライザル3秒前</BeforeTextToSpeak>
      <BeforeAdvancedConfig>
        <IsEnabled>false</IsEnabled>
        <ToMainDevice>true</ToMainDevice>
        <ToSubDevice>false</ToSubDevice>
        <ToDicordTextChat>false</ToDicordTextChat>
        <Palette>Default</Palette>
      </BeforeAdvancedConfig>
      <TimeupTextToSpeak />
      <TimeupAdvancedConfig>
        <IsEnabled>false</IsEnabled>
        <ToMainDevice>true</ToMainDevice>
        <ToSubDevice>false</ToSubDevice>
        <ToDicordTextChat>false</ToDicordTextChat>
        <Palette>Default</Palette>
      </TimeupAdvancedConfig>
      <MatchSound />
      <OverSound />
      <BeforeSound />
      <TimeupSound />
    </SpellTimer>
    <SpellTimer>
      <SortPriority>0</SortPriority>
      <IsChecked>false</IsChecked>
      <IsExpanded>false</IsExpanded>
      <Enabled>true</Enabled>
      <IsCircleStyle>true</IsCircleStyle>
      <TitleVerticalAlignmentInCircle>Center</TitleVerticalAlignmentInCircle>
      <Left>0</Left>
      <Top>0</Top>
      <ID>238</ID>
      <Guid>f98363e4-5cb1-46d3-87e1-65caa9f66d06</Guid>
      <PanelID>682207e0-c8bb-40ee-9f5a-687041c092fd</PanelID>
      <Panel>シナジースキル効果時間表示</Panel>
      <SpellTitle>ボーライド</SpellTitle>
      <RegexEnabled>true</RegexEnabled>
      <Keyword>^00:&lt;id4&gt;:&lt;mex&gt;の「ボーライド」$</Keyword>
      <KeywordForExtend1 />
      <KeywordForExtend2 />
      <RecastTime>360</RecastTime>
      <DelayToShow>0</DelayToShow>
      <RecastTimeExtending1>0</RecastTimeExtending1>
      <RecastTimeExtending2>0</RecastTimeExtending2>
      <RecastTimeExtending3>0</RecastTimeExtending3>
      <OverlapRecastTime>true</OverlapRecastTime>
      <IsNotResetBarOnExtended>false</IsNotResetBarOnExtended>
      <ProgressBarVisible>true</ProgressBarVisible>
      <Font FontFamily="Impact" Size="14" Stretch="Condensed" Style="Normal" Weight="Normal" />
      <FontColor>#FFFFFF</FontColor>
      <FontOutlineColor>#696969</FontOutlineColor>
      <WarningTime>0</WarningTime>
      <ChangeFontColorsWhenWarning>false</ChangeFontColorsWhenWarning>
      <WarningFontColor>#FFFFFF</WarningFontColor>
      <WarningFontOutlineColor>#FF4500</WarningFontOutlineColor>
      <ChangeFontColorWhenContainsMe>false</ChangeFontColorWhenContainsMe>
      <BarWidth>35</BarWidth>
      <BarHeight>3</BarHeight>
      <BarColor>#FFFFFF</BarColor>
      <BarOutlineColor>#191970</BarOutlineColor>
      <BarBlurRadius>0</BarBlurRadius>
      <BackgroundColor>#FFFFFF</BackgroundColor>
      <BackgroundAlpha>0</BackgroundAlpha>
      <DisplayNo>3</DisplayNo>
      <DontHide>false</DontHide>
      <IsHideInNotCombat>false</IsHideInNotCombat>
      <ExtendBeyondOriginalRecastTime>false</ExtendBeyondOriginalRecastTime>
      <HideSpellName>true</HideSpellName>
      <HideCounter>false</HideCounter>
      <IsCounterToCenter>false</IsCounterToCenter>
      <IsReverse>false</IsReverse>
      <MatchDateTime>0001-01-01T00:00:00</MatchDateTime>
      <UseHotbarRecastTime>false</UseHotbarRecastTime>
      <HotbarName />
      <ReduceIconBrightness>true</ReduceIconBrightness>
      <SpellIcon>16152_ボーライド.png</SpellIcon>
      <SpellIconSize>29</SpellIconSize>
      <IsNotResetAtWipeout>false</IsNotResetAtWipeout>
      <TimeupHide>false</TimeupHide>
      <ToInstance>false</ToInstance>
      <UpperLimitOfExtension>0</UpperLimitOfExtension>
      <BlinkTime>0</BlinkTime>
      <BlinkIcon>false</BlinkIcon>
      <BlinkBar>false</BlinkBar>
      <JobFilter>37</JobFilter>
      <PartyJobFilter />
      <PartyCompositionFilter />
      <ZoneFilter />
      <TimersMustRunningForStart />
      <TimersMustStoppingForStart />
      <ExpressionFilter>
        <expression />
        <expression />
        <expression />
        <expression />
      </ExpressionFilter>
      <IsSequentialTTS>false</IsSequentialTTS>
      <MatchTextToSpeak />
      <MatchAdvancedConfig>
        <IsEnabled>false</IsEnabled>
        <ToMainDevice>true</ToMainDevice>
        <ToSubDevice>false</ToSubDevice>
        <ToDicordTextChat>false</ToDicordTextChat>
        <Palette>Default</Palette>
      </MatchAdvancedConfig>
      <OverTime>0</OverTime>
      <OverTextToSpeak />
      <OverAdvancedConfig>
        <IsEnabled>false</IsEnabled>
        <ToMainDevice>true</ToMainDevice>
        <ToSubDevice>false</ToSubDevice>
        <ToDicordTextChat>false</ToDicordTextChat>
        <Palette>Default</Palette>
      </OverAdvancedConfig>
      <BeforeTime>3</BeforeTime>
      <BeforeTextToSpeak>ボーラ3秒前</BeforeTextToSpeak>
      <BeforeAdvancedConfig>
        <IsEnabled>false</IsEnabled>
        <ToMainDevice>true</ToMainDevice>
        <ToSubDevice>false</ToSubDevice>
        <ToDicordTextChat>false</ToDicordTextChat>
        <Palette>Default</Palette>
      </BeforeAdvancedConfig>
      <TimeupTextToSpeak />
      <TimeupAdvancedConfig>
        <IsEnabled>false</IsEnabled>
        <ToMainDevice>true</ToMainDevice>
        <ToSubDevice>false</ToSubDevice>
        <ToDicordTextChat>false</ToDicordTextChat>
        <Palette>Default</Palette>
      </TimeupAdvancedConfig>
      <MatchSound />
      <OverSound />
      <BeforeSound />
      <TimeupSound />
    </SpellTimer>
    <SpellTimer>
      <SortPriority>0</SortPriority>
      <IsChecked>false</IsChecked>
      <IsExpanded>false</IsExpanded>
      <Enabled>true</Enabled>
      <IsCircleStyle>true</IsCircleStyle>
      <TitleVerticalAlignmentInCircle>Center</TitleVerticalAlignmentInCircle>
      <Left>0</Left>
      <Top>0</Top>
      <ID>235</ID>
      <Guid>201e7ced-656b-46e8-a843-b1aee7ad51eb</Guid>
      <PanelID>682207e0-c8bb-40ee-9f5a-687041c092fd</PanelID>
      <Panel>シナジースキル効果時間表示</Panel>
      <SpellTitle>シャーク</SpellTitle>
      <RegexEnabled>true</RegexEnabled>
      <Keyword>^00:&lt;id4&gt;:&lt;mex&gt;の「シャーク」$</Keyword>
      <KeywordForExtend1 />
      <KeywordForExtend2 />
      <RecastTime>120</RecastTime>
      <DelayToShow>0</DelayToShow>
      <RecastTimeExtending1>0</RecastTimeExtending1>
      <RecastTimeExtending2>0</RecastTimeExtending2>
      <RecastTimeExtending3>0</RecastTimeExtending3>
      <OverlapRecastTime>true</OverlapRecastTime>
      <IsNotResetBarOnExtended>false</IsNotResetBarOnExtended>
      <ProgressBarVisible>true</ProgressBarVisible>
      <Font FontFamily="Impact" Size="14" Stretch="Condensed" Style="Normal" Weight="Normal" />
      <FontColor>#FFFFFF</FontColor>
      <FontOutlineColor>#696969</FontOutlineColor>
      <WarningTime>0</WarningTime>
      <ChangeFontColorsWhenWarning>false</ChangeFontColorsWhenWarning>
      <WarningFontColor>#FFFFFF</WarningFontColor>
      <WarningFontOutlineColor>#FF4500</WarningFontOutlineColor>
      <ChangeFontColorWhenContainsMe>false</ChangeFontColorWhenContainsMe>
      <BarWidth>35</BarWidth>
      <BarHeight>3</BarHeight>
      <BarColor>#FFFFFF</BarColor>
      <BarOutlineColor>#191970</BarOutlineColor>
      <BarBlurRadius>0</BarBlurRadius>
      <BackgroundColor>#FFFFFF</BackgroundColor>
      <BackgroundAlpha>0</BackgroundAlpha>
      <DisplayNo>4</DisplayNo>
      <DontHide>false</DontHide>
      <IsHideInNotCombat>false</IsHideInNotCombat>
      <ExtendBeyondOriginalRecastTime>false</ExtendBeyondOriginalRecastTime>
      <HideSpellName>true</HideSpellName>
      <HideCounter>false</HideCounter>
      <IsCounterToCenter>false</IsCounterToCenter>
      <IsReverse>false</IsReverse>
      <MatchDateTime>0001-01-01T00:00:00</MatchDateTime>
      <UseHotbarRecastTime>false</UseHotbarRecastTime>
      <HotbarName />
      <ReduceIconBrightness>true</ReduceIconBrightness>
      <SpellIcon>7537_シャーク.png</SpellIcon>
      <SpellIconSize>29</SpellIconSize>
      <IsNotResetAtWipeout>false</IsNotResetAtWipeout>
      <TimeupHide>false</TimeupHide>
      <ToInstance>false</ToInstance>
      <UpperLimitOfExtension>0</UpperLimitOfExtension>
      <BlinkTime>5</BlinkTime>
      <BlinkIcon>false</BlinkIcon>
      <BlinkBar>true</BlinkBar>
      <JobFilter>1,3,19,21,32,37</JobFilter>
      <PartyJobFilter />
      <PartyCompositionFilter />
      <ZoneFilter />
      <TimersMustRunningForStart />
      <TimersMustStoppingForStart />
      <ExpressionFilter>
        <expression />
        <expression />
        <expression />
        <expression />
      </ExpressionFilter>
      <IsSequentialTTS>false</IsSequentialTTS>
      <MatchTextToSpeak />
      <MatchAdvancedConfig>
        <IsEnabled>false</IsEnabled>
        <ToMainDevice>true</ToMainDevice>
        <ToSubDevice>false</ToSubDevice>
        <ToDicordTextChat>false</ToDicordTextChat>
        <Palette>Default</Palette>
      </MatchAdvancedConfig>
      <OverTime>0</OverTime>
      <OverTextToSpeak />
      <OverAdvancedConfig>
        <IsEnabled>false</IsEnabled>
        <ToMainDevice>true</ToMainDevice>
        <ToSubDevice>false</ToSubDevice>
        <ToDicordTextChat>false</ToDicordTextChat>
        <Palette>Default</Palette>
      </OverAdvancedConfig>
      <BeforeTime>3</BeforeTime>
      <BeforeTextToSpeak>シャーク3秒前</BeforeTextToSpeak>
      <BeforeAdvancedConfig>
        <IsEnabled>false</IsEnabled>
        <ToMainDevice>true</ToMainDevice>
        <ToSubDevice>false</ToSubDevice>
        <ToDicordTextChat>false</ToDicordTextChat>
        <Palette>Default</Palette>
      </BeforeAdvancedConfig>
      <TimeupTextToSpeak />
      <TimeupAdvancedConfig>
        <IsEnabled>false</IsEnabled>
        <ToMainDevice>true</ToMainDevice>
        <ToSubDevice>false</ToSubDevice>
        <ToDicordTextChat>false</ToDicordTextChat>
        <Palette>Default</Palette>
      </TimeupAdvancedConfig>
      <MatchSound />
      <OverSound />
      <BeforeSound />
      <TimeupSound />
    </SpellTimer>
    <SpellTimer>
      <SortPriority>0</SortPriority>
      <IsChecked>false</IsChecked>
      <IsExpanded>false</IsExpanded>
      <Enabled>true</Enabled>
      <IsCircleStyle>true</IsCircleStyle>
      <TitleVerticalAlignmentInCircle>Center</TitleVerticalAlignmentInCircle>
      <Left>0</Left>
      <Top>0</Top>
      <ID>237</ID>
      <Guid>54639a91-8a2a-438f-9627-bd262f17cdb6</Guid>
      <PanelID>682207e0-c8bb-40ee-9f5a-687041c092fd</PanelID>
      <Panel>シナジースキル効果時間表示</Panel>
      <SpellTitle>ネビュラ</SpellTitle>
      <RegexEnabled>true</RegexEnabled>
      <Keyword>^00:&lt;id4&gt;:&lt;mex&gt;の「ネビュラ」$</Keyword>
      <KeywordForExtend1 />
      <KeywordForExtend2 />
      <RecastTime>120</RecastTime>
      <DelayToShow>0</DelayToShow>
      <RecastTimeExtending1>0</RecastTimeExtending1>
      <RecastTimeExtending2>0</RecastTimeExtending2>
      <RecastTimeExtending3>0</RecastTimeExtending3>
      <OverlapRecastTime>true</OverlapRecastTime>
      <IsNotResetBarOnExtended>false</IsNotResetBarOnExtended>
      <ProgressBarVisible>true</ProgressBarVisible>
      <Font FontFamily="Impact" Size="14" Stretch="Condensed" Style="Normal" Weight="Normal" />
      <FontColor>#FFFFFF</FontColor>
      <FontOutlineColor>#696969</FontOutlineColor>
      <WarningTime>0</WarningTime>
      <ChangeFontColorsWhenWarning>false</ChangeFontColorsWhenWarning>
      <WarningFontColor>#FFFFFF</WarningFontColor>
      <WarningFontOutlineColor>#FF4500</WarningFontOutlineColor>
      <ChangeFontColorWhenContainsMe>false</ChangeFontColorWhenContainsMe>
      <BarWidth>35</BarWidth>
      <BarHeight>3</BarHeight>
      <BarColor>#FFFFFF</BarColor>
      <BarOutlineColor>#191970</BarOutlineColor>
      <BarBlurRadius>0</BarBlurRadius>
      <BackgroundColor>#FFFFFF</BackgroundColor>
      <BackgroundAlpha>0</BackgroundAlpha>
      <DisplayNo>5</DisplayNo>
      <DontHide>false</DontHide>
      <IsHideInNotCombat>false</IsHideInNotCombat>
      <ExtendBeyondOriginalRecastTime>false</ExtendBeyondOriginalRecastTime>
      <HideSpellName>true</HideSpellName>
      <HideCounter>false</HideCounter>
      <IsCounterToCenter>false</IsCounterToCenter>
      <IsReverse>false</IsReverse>
      <MatchDateTime>0001-01-01T00:00:00</MatchDateTime>
      <UseHotbarRecastTime>false</UseHotbarRecastTime>
      <HotbarName />
      <ReduceIconBrightness>true</ReduceIconBrightness>
      <SpellIcon>16148_ネビュラ.png</SpellIcon>
      <SpellIconSize>29</SpellIconSize>
      <IsNotResetAtWipeout>false</IsNotResetAtWipeout>
      <TimeupHide>false</TimeupHide>
      <ToInstance>false</ToInstance>
      <UpperLimitOfExtension>0</UpperLimitOfExtension>
      <BlinkTime>5</BlinkTime>
      <BlinkIcon>false</BlinkIcon>
      <BlinkBar>true</BlinkBar>
      <JobFilter>1,3,19,21,32,37</JobFilter>
      <PartyJobFilter />
      <PartyCompositionFilter />
      <ZoneFilter />
      <TimersMustRunningForStart />
      <TimersMustStoppingForStart />
      <ExpressionFilter>
        <expression />
        <expression />
        <expression />
        <expression />
      </ExpressionFilter>
      <IsSequentialTTS>false</IsSequentialTTS>
      <MatchTextToSpeak />
      <MatchAdvancedConfig>
        <IsEnabled>false</IsEnabled>
        <ToMainDevice>true</ToMainDevice>
        <ToSubDevice>false</ToSubDevice>
        <ToDicordTextChat>false</ToDicordTextChat>
        <Palette>Default</Palette>
      </MatchAdvancedConfig>
      <OverTime>0</OverTime>
      <OverTextToSpeak />
      <OverAdvancedConfig>
        <IsEnabled>false</IsEnabled>
        <ToMainDevice>true</ToMainDevice>
        <ToSubDevice>false</ToSubDevice>
        <ToDicordTextChat>false</ToDicordTextChat>
        <Palette>Default</Palette>
      </OverAdvancedConfig>
      <BeforeTime>3</BeforeTime>
      <BeforeTextToSpeak>ネビュラ3秒前</BeforeTextToSpeak>
      <BeforeAdvancedConfig>
        <IsEnabled>false</IsEnabled>
        <ToMainDevice>true</ToMainDevice>
        <ToSubDevice>false</ToSubDevice>
        <ToDicordTextChat>false</ToDicordTextChat>
        <Palette>Default</Palette>
      </BeforeAdvancedConfig>
      <TimeupTextToSpeak />
      <TimeupAdvancedConfig>
        <IsEnabled>false</IsEnabled>
        <ToMainDevice>true</ToMainDevice>
        <ToSubDevice>false</ToSubDevice>
        <ToDicordTextChat>false</ToDicordTextChat>
        <Palette>Default</Palette>
      </TimeupAdvancedConfig>
      <MatchSound />
      <OverSound />
      <BeforeSound />
      <TimeupSound />
    </SpellTimer>
    <SpellTimer>
      <SortPriority>0</SortPriority>
      <IsChecked>false</IsChecked>
      <IsExpanded>false</IsExpanded>
      <Enabled>true</Enabled>
      <IsCircleStyle>true</IsCircleStyle>
      <TitleVerticalAlignmentInCircle>Center</TitleVerticalAlignmentInCircle>
      <Left>0</Left>
      <Top>0</Top>
      <ID>12</ID>
      <Guid>e18968b3-e006-4e0b-b290-96f114dc05be</Guid>
      <PanelID>682207e0-c8bb-40ee-9f5a-687041c092fd</PanelID>
      <Panel>シナジースキル効果時間表示</Panel>
      <SpellTitle>ハート・オブ・ライト</SpellTitle>
      <RegexEnabled>true</RegexEnabled>
      <Keyword>^00:&lt;id4&gt;:&lt;mex&gt;の「ハート・オブ・ライト」$</Keyword>
      <KeywordForExtend1 />
      <KeywordForExtend2 />
      <RecastTime>90</RecastTime>
      <DelayToShow>0</DelayToShow>
      <RecastTimeExtending1>0</RecastTimeExtending1>
      <RecastTimeExtending2>0</RecastTimeExtending2>
      <RecastTimeExtending3>0</RecastTimeExtending3>
      <OverlapRecastTime>true</OverlapRecastTime>
      <IsNotResetBarOnExtended>false</IsNotResetBarOnExtended>
      <ProgressBarVisible>true</ProgressBarVisible>
      <Font FontFamily="Impact" Size="14" Stretch="Condensed" Style="Normal" Weight="Normal" />
      <FontColor>#FFFFFF</FontColor>
      <FontOutlineColor>#696969</FontOutlineColor>
      <WarningTime>0</WarningTime>
      <ChangeFontColorsWhenWarning>false</ChangeFontColorsWhenWarning>
      <WarningFontColor>#FFFFFF</WarningFontColor>
      <WarningFontOutlineColor>#FF4500</WarningFontOutlineColor>
      <ChangeFontColorWhenContainsMe>false</ChangeFontColorWhenContainsMe>
      <BarWidth>35</BarWidth>
      <BarHeight>3</BarHeight>
      <BarColor>#FFFFFF</BarColor>
      <BarOutlineColor>#191970</BarOutlineColor>
      <BarBlurRadius>0</BarBlurRadius>
      <BackgroundColor>#FFFFFF</BackgroundColor>
      <BackgroundAlpha>0</BackgroundAlpha>
      <DisplayNo>6</DisplayNo>
      <DontHide>false</DontHide>
      <IsHideInNotCombat>false</IsHideInNotCombat>
      <ExtendBeyondOriginalRecastTime>false</ExtendBeyondOriginalRecastTime>
      <HideSpellName>true</HideSpellName>
      <HideCounter>false</HideCounter>
      <IsCounterToCenter>false</IsCounterToCenter>
      <IsReverse>false</IsReverse>
      <MatchDateTime>0001-01-01T00:00:00</MatchDateTime>
      <UseHotbarRecastTime>false</UseHotbarRecastTime>
      <HotbarName />
      <ReduceIconBrightness>true</ReduceIconBrightness>
      <SpellIcon>16160_ハート・オブ・ライト.png</SpellIcon>
      <SpellIconSize>29</SpellIconSize>
      <IsNotResetAtWipeout>false</IsNotResetAtWipeout>
      <TimeupHide>false</TimeupHide>
      <ToInstance>false</ToInstance>
      <UpperLimitOfExtension>0</UpperLimitOfExtension>
      <BlinkTime>5</BlinkTime>
      <BlinkIcon>false</BlinkIcon>
      <BlinkBar>true</BlinkBar>
      <JobFilter>1,3,19,21,32,37</JobFilter>
      <PartyJobFilter />
      <PartyCompositionFilter />
      <ZoneFilter />
      <TimersMustRunningForStart />
      <TimersMustStoppingForStart />
      <ExpressionFilter>
        <expression />
        <expression />
        <expression />
        <expression />
      </ExpressionFilter>
      <IsSequentialTTS>false</IsSequentialTTS>
      <MatchTextToSpeak />
      <MatchAdvancedConfig>
        <IsEnabled>false</IsEnabled>
        <ToMainDevice>true</ToMainDevice>
        <ToSubDevice>false</ToSubDevice>
        <ToDicordTextChat>false</ToDicordTextChat>
        <Palette>Default</Palette>
      </MatchAdvancedConfig>
      <OverTime>0</OverTime>
      <OverTextToSpeak />
      <OverAdvancedConfig>
        <IsEnabled>false</IsEnabled>
        <ToMainDevice>true</ToMainDevice>
        <ToSubDevice>false</ToSubDevice>
        <ToDicordTextChat>false</ToDicordTextChat>
        <Palette>Default</Palette>
      </OverAdvancedConfig>
      <BeforeTime>3</BeforeTime>
      <BeforeTextToSpeak>ライト3秒前</BeforeTextToSpeak>
      <BeforeAdvancedConfig>
        <IsEnabled>false</IsEnabled>
        <ToMainDevice>true</ToMainDevice>
        <ToSubDevice>false</ToSubDevice>
        <ToDicordTextChat>false</ToDicordTextChat>
        <Palette>Default</Palette>
      </BeforeAdvancedConfig>
      <TimeupTextToSpeak />
      <TimeupAdvancedConfig>
        <IsEnabled>false</IsEnabled>
        <ToMainDevice>true</ToMainDevice>
        <ToSubDevice>false</ToSubDevice>
        <ToDicordTextChat>false</ToDicordTextChat>
        <Palette>Default</Palette>
      </TimeupAdvancedConfig>
      <MatchSound />
      <OverSound />
      <BeforeSound />
      <TimeupSound />
    </SpellTimer>
    <SpellTimer>
      <SortPriority>0</SortPriority>
      <IsChecked>false</IsChecked>
      <IsExpanded>false</IsExpanded>
      <Enabled>true</Enabled>
      <IsCircleStyle>true</IsCircleStyle>
      <TitleVerticalAlignmentInCircle>Center</TitleVerticalAlignmentInCircle>
      <Left>0</Left>
      <Top>0</Top>
      <ID>13</ID>
      <Guid>e38a9141-d881-4981-b36c-011f6b1c59e5</Guid>
      <PanelID>682207e0-c8bb-40ee-9f5a-687041c092fd</PanelID>
      <Panel>シナジースキル効果時間表示</Panel>
      <SpellTitle>オーロラ</SpellTitle>
      <RegexEnabled>true</RegexEnabled>
      <Keyword>^00:&lt;id4&gt;:&lt;mex&gt;の「オーロラ」$</Keyword>
      <KeywordForExtend1 />
      <KeywordForExtend2 />
      <RecastTime>60</RecastTime>
      <DelayToShow>0</DelayToShow>
      <RecastTimeExtending1>0</RecastTimeExtending1>
      <RecastTimeExtending2>0</RecastTimeExtending2>
      <RecastTimeExtending3>0</RecastTimeExtending3>
      <OverlapRecastTime>true</OverlapRecastTime>
      <IsNotResetBarOnExtended>false</IsNotResetBarOnExtended>
      <ProgressBarVisible>true</ProgressBarVisible>
      <Font FontFamily="Impact" Size="14" Stretch="Condensed" Style="Normal" Weight="Normal" />
      <FontColor>#FFFFFF</FontColor>
      <FontOutlineColor>#0000FF</FontOutlineColor>
      <WarningTime>0</WarningTime>
      <ChangeFontColorsWhenWarning>false</ChangeFontColorsWhenWarning>
      <WarningFontColor>Transparent</WarningFontColor>
      <WarningFontOutlineColor>Transparent</WarningFontOutlineColor>
      <ChangeFontColorWhenContainsMe>false</ChangeFontColorWhenContainsMe>
      <BarWidth>35</BarWidth>
      <BarHeight>3</BarHeight>
      <BarColor>#FFFFFF</BarColor>
      <BarOutlineColor>#191970</BarOutlineColor>
      <BarBlurRadius>0</BarBlurRadius>
      <BackgroundColor>#FFFFFF</BackgroundColor>
      <BackgroundAlpha>0</BackgroundAlpha>
      <DisplayNo>1101</DisplayNo>
      <DontHide>false</DontHide>
      <IsHideInNotCombat>false</IsHideInNotCombat>
      <ExtendBeyondOriginalRecastTime>false</ExtendBeyondOriginalRecastTime>
      <HideSpellName>true</HideSpellName>
      <HideCounter>false</HideCounter>
      <IsCounterToCenter>false</IsCounterToCenter>
      <IsReverse>false</IsReverse>
      <MatchDateTime>0001-01-01T00:00:00</MatchDateTime>
      <UseHotbarRecastTime>false</UseHotbarRecastTime>
      <HotbarName />
      <ReduceIconBrightness>true</ReduceIconBrightness>
      <SpellIcon>16151_オーロラ.png</SpellIcon>
      <SpellIconSize>29</SpellIconSize>
      <IsNotResetAtWipeout>false</IsNotResetAtWipeout>
      <TimeupHide>false</TimeupHide>
      <ToInstance>false</ToInstance>
      <UpperLimitOfExtension>0</UpperLimitOfExtension>
      <BlinkTime>5</BlinkTime>
      <BlinkIcon>false</BlinkIcon>
      <BlinkBar>true</BlinkBar>
      <JobFilter>1,3,19,21,32,37</JobFilter>
      <PartyJobFilter />
      <PartyCompositionFilter />
      <ZoneFilter />
      <TimersMustRunningForStart />
      <TimersMustStoppingForStart />
      <ExpressionFilter>
        <expression />
        <expression />
        <expression />
        <expression />
      </ExpressionFilter>
      <IsSequentialTTS>false</IsSequentialTTS>
      <MatchTextToSpeak />
      <MatchAdvancedConfig>
        <IsEnabled>false</IsEnabled>
        <ToMainDevice>true</ToMainDevice>
        <ToSubDevice>false</ToSubDevice>
        <ToDicordTextChat>false</ToDicordTextChat>
        <Palette>Default</Palette>
      </MatchAdvancedConfig>
      <OverTime>0</OverTime>
      <OverTextToSpeak />
      <OverAdvancedConfig>
        <IsEnabled>false</IsEnabled>
        <ToMainDevice>true</ToMainDevice>
        <ToSubDevice>false</ToSubDevice>
        <ToDicordTextChat>false</ToDicordTextChat>
        <Palette>Default</Palette>
      </OverAdvancedConfig>
      <BeforeTime>3</BeforeTime>
      <BeforeTextToSpeak>オーロラ3秒前</BeforeTextToSpeak>
      <BeforeAdvancedConfig>
        <IsEnabled>false</IsEnabled>
        <ToMainDevice>true</ToMainDevice>
        <ToSubDevice>false</ToSubDevice>
        <ToDicordTextChat>false</ToDicordTextChat>
        <Palette>Default</Palette>
      </BeforeAdvancedConfig>
      <TimeupTextToSpeak />
      <TimeupAdvancedConfig>
        <IsEnabled>false</IsEnabled>
        <ToMainDevice>true</ToMainDevice>
        <ToSubDevice>false</ToSubDevice>
        <ToDicordTextChat>false</ToDicordTextChat>
        <Palette>Default</Palette>
      </TimeupAdvancedConfig>
      <MatchSound />
      <OverSound />
      <BeforeSound />
      <TimeupSound />
    </SpellTimer>
    <SpellTimer>
      <SortPriority>0</SortPriority>
      <IsChecked>false</IsChecked>
      <IsExpanded>false</IsExpanded>
      <Enabled>true</Enabled>
      <IsCircleStyle>true</IsCircleStyle>
      <TitleVerticalAlignmentInCircle>Center</TitleVerticalAlignmentInCircle>
      <Left>0</Left>
      <Top>0</Top>
      <ID>14</ID>
      <Guid>d3638f30-38e3-4a9d-9592-a6f351ff396d</Guid>
      <PanelID>682207e0-c8bb-40ee-9f5a-687041c092fd</PanelID>
      <Panel>シナジースキル効果時間表示</Panel>
      <SpellTitle>カモフラージュ</SpellTitle>
      <RegexEnabled>true</RegexEnabled>
      <Keyword>^00:&lt;id4&gt;:&lt;mex&gt;の「カモフラージュ」$</Keyword>
      <KeywordForExtend1 />
      <KeywordForExtend2 />
      <RecastTime>90</RecastTime>
      <DelayToShow>0</DelayToShow>
      <RecastTimeExtending1>0</RecastTimeExtending1>
      <RecastTimeExtending2>0</RecastTimeExtending2>
      <RecastTimeExtending3>0</RecastTimeExtending3>
      <OverlapRecastTime>true</OverlapRecastTime>
      <IsNotResetBarOnExtended>false</IsNotResetBarOnExtended>
      <ProgressBarVisible>true</ProgressBarVisible>
      <Font FontFamily="Impact" Size="14" Stretch="Condensed" Style="Normal" Weight="Normal" />
      <FontColor>#FFFFFF</FontColor>
      <FontOutlineColor>#0000FF</FontOutlineColor>
      <WarningTime>0</WarningTime>
      <ChangeFontColorsWhenWarning>false</ChangeFontColorsWhenWarning>
      <WarningFontColor>Transparent</WarningFontColor>
      <WarningFontOutlineColor>Transparent</WarningFontOutlineColor>
      <ChangeFontColorWhenContainsMe>false</ChangeFontColorWhenContainsMe>
      <BarWidth>35</BarWidth>
      <BarHeight>3</BarHeight>
      <BarColor>#FFFFFF</BarColor>
      <BarOutlineColor>#191970</BarOutlineColor>
      <BarBlurRadius>0</BarBlurRadius>
      <BackgroundColor>#FFFFFF</BackgroundColor>
      <BackgroundAlpha>0</BackgroundAlpha>
      <DisplayNo>1102</DisplayNo>
      <DontHide>false</DontHide>
      <IsHideInNotCombat>false</IsHideInNotCombat>
      <ExtendBeyondOriginalRecastTime>false</ExtendBeyondOriginalRecastTime>
      <HideSpellName>true</HideSpellName>
      <HideCounter>false</HideCounter>
      <IsCounterToCenter>false</IsCounterToCenter>
      <IsReverse>false</IsReverse>
      <MatchDateTime>0001-01-01T00:00:00</MatchDateTime>
      <UseHotbarRecastTime>false</UseHotbarRecastTime>
      <HotbarName />
      <ReduceIconBrightness>false</ReduceIconBrightness>
      <SpellIcon>16140_カモフラージュ.png</SpellIcon>
      <SpellIconSize>29</SpellIconSize>
      <IsNotResetAtWipeout>false</IsNotResetAtWipeout>
      <TimeupHide>false</TimeupHide>
      <ToInstance>false</ToInstance>
      <UpperLimitOfExtension>0</UpperLimitOfExtension>
      <BlinkTime>5</BlinkTime>
      <BlinkIcon>false</BlinkIcon>
      <BlinkBar>false</BlinkBar>
      <JobFilter>1,3,19,21,32,37</JobFilter>
      <PartyJobFilter />
      <PartyCompositionFilter />
      <ZoneFilter />
      <TimersMustRunningForStart />
      <TimersMustStoppingForStart />
      <ExpressionFilter>
        <expression />
        <expression />
        <expression />
        <expression />
      </ExpressionFilter>
      <IsSequentialTTS>false</IsSequentialTTS>
      <MatchTextToSpeak />
      <MatchAdvancedConfig>
        <IsEnabled>false</IsEnabled>
        <ToMainDevice>true</ToMainDevice>
        <ToSubDevice>false</ToSubDevice>
        <ToDicordTextChat>false</ToDicordTextChat>
        <Palette>Default</Palette>
      </MatchAdvancedConfig>
      <OverTime>0</OverTime>
      <OverTextToSpeak />
      <OverAdvancedConfig>
        <IsEnabled>false</IsEnabled>
        <ToMainDevice>true</ToMainDevice>
        <ToSubDevice>false</ToSubDevice>
        <ToDicordTextChat>false</ToDicordTextChat>
        <Palette>Default</Palette>
      </OverAdvancedConfig>
      <BeforeTime>3</BeforeTime>
      <BeforeTextToSpeak>カモフラ3秒前</BeforeTextToSpeak>
      <BeforeAdvancedConfig>
        <IsEnabled>false</IsEnabled>
        <ToMainDevice>true</ToMainDevice>
        <ToSubDevice>false</ToSubDevice>
        <ToDicordTextChat>false</ToDicordTextChat>
        <Palette>Default</Palette>
      </BeforeAdvancedConfig>
      <TimeupTextToSpeak />
      <TimeupAdvancedConfig>
        <IsEnabled>false</IsEnabled>
        <ToMainDevice>true</ToMainDevice>
        <ToSubDevice>false</ToSubDevice>
        <ToDicordTextChat>false</ToDicordTextChat>
        <Palette>Default</Palette>
      </TimeupAdvancedConfig>
      <MatchSound />
      <OverSound />
      <BeforeSound />
      <TimeupSound />
    </SpellTimer>
    <SpellTimer>
      <SortPriority>0</SortPriority>
      <IsChecked>false</IsChecked>
      <IsExpanded>false</IsExpanded>
      <Enabled>true</Enabled>
      <IsCircleStyle>false</IsCircleStyle>
      <TitleVerticalAlignmentInCircle>Center</TitleVerticalAlignmentInCircle>
      <Left>-39</Left>
      <Top>0</Top>
      <ID>23</ID>
      <Guid>6439b056-e246-4cc5-9b3b-cf89cea5def9</Guid>
      <PanelID>682207e0-c8bb-40ee-9f5a-687041c092fd</PanelID>
      <Panel>シナジースキル効果時間表示</Panel>
      <SpellTitle>ナイトのリプ</SpellTitle>
      <RegexEnabled>true</RegexEnabled>
      <Keyword>^00:&lt;id4&gt;:&lt;2ex&gt;の「リプライザル」$</Keyword>
      <KeywordForExtend1 />
      <KeywordForExtend2 />
      <RecastTime>60</RecastTime>
      <DelayToShow>0</DelayToShow>
      <RecastTimeExtending1>0</RecastTimeExtending1>
      <RecastTimeExtending2>0</RecastTimeExtending2>
      <RecastTimeExtending3>0</RecastTimeExtending3>
      <OverlapRecastTime>true</OverlapRecastTime>
      <IsNotResetBarOnExtended>false</IsNotResetBarOnExtended>
      <ProgressBarVisible>false</ProgressBarVisible>
      <Font FontFamily="Impact" Size="14" Stretch="Condensed" Style="Normal" Weight="Normal" />
      <FontColor>#FFFFFF</FontColor>
      <FontOutlineColor>#696969</FontOutlineColor>
      <WarningTime>0</WarningTime>
      <ChangeFontColorsWhenWarning>false</ChangeFontColorsWhenWarning>
      <WarningFontColor>#FFFFFF</WarningFontColor>
      <WarningFontOutlineColor>#FF4500</WarningFontOutlineColor>
      <ChangeFontColorWhenContainsMe>false</ChangeFontColorWhenContainsMe>
      <BarWidth>35</BarWidth>
      <BarHeight>3</BarHeight>
      <BarColor>#FFFFFF</BarColor>
      <BarOutlineColor>#191970</BarOutlineColor>
      <BarBlurRadius>0</BarBlurRadius>
      <BackgroundColor>#FFFFFF</BackgroundColor>
      <BackgroundAlpha>0</BackgroundAlpha>
      <DisplayNo>1103</DisplayNo>
      <DontHide>false</DontHide>
      <IsHideInNotCombat>false</IsHideInNotCombat>
      <ExtendBeyondOriginalRecastTime>false</ExtendBeyondOriginalRecastTime>
      <HideSpellName>false</HideSpellName>
      <HideCounter>false</HideCounter>
      <IsCounterToCenter>false</IsCounterToCenter>
      <IsReverse>false</IsReverse>
      <MatchDateTime>0001-01-01T00:00:00</MatchDateTime>
      <UseHotbarRecastTime>false</UseHotbarRecastTime>
      <HotbarName />
      <ReduceIconBrightness>true</ReduceIconBrightness>
      <SpellIcon>7535_リプライザル.png</SpellIcon>
      <SpellIconSize>29</SpellIconSize>
      <IsNotResetAtWipeout>false</IsNotResetAtWipeout>
      <TimeupHide>false</TimeupHide>
      <ToInstance>false</ToInstance>
      <UpperLimitOfExtension>0</UpperLimitOfExtension>
      <BlinkTime>0</BlinkTime>
      <BlinkIcon>false</BlinkIcon>
      <BlinkBar>false</BlinkBar>
      <JobFilter />
      <PartyJobFilter>1,19</PartyJobFilter>
      <PartyCompositionFilter />
      <ZoneFilter />
      <TimersMustRunningForStart />
      <TimersMustStoppingForStart />
      <ExpressionFilter>
        <expression target="&lt;2&gt;" regex="&lt;TANK&gt;" />
        <expression target="" />
        <expression />
        <expression />
      </ExpressionFilter>
      <IsSequentialTTS>false</IsSequentialTTS>
      <MatchTextToSpeak>ナイトのリプ</MatchTextToSpeak>
      <MatchAdvancedConfig>
        <IsEnabled>false</IsEnabled>
        <ToMainDevice>true</ToMainDevice>
        <ToSubDevice>false</ToSubDevice>
        <ToDicordTextChat>false</ToDicordTextChat>
        <Palette>Default</Palette>
      </MatchAdvancedConfig>
      <OverTime>0</OverTime>
      <OverTextToSpeak />
      <OverAdvancedConfig>
        <IsEnabled>false</IsEnabled>
        <ToMainDevice>true</ToMainDevice>
        <ToSubDevice>false</ToSubDevice>
        <ToDicordTextChat>false</ToDicordTextChat>
        <Palette>Default</Palette>
      </OverAdvancedConfig>
      <BeforeTime>0</BeforeTime>
      <BeforeTextToSpeak />
      <BeforeAdvancedConfig>
        <IsEnabled>false</IsEnabled>
        <ToMainDevice>true</ToMainDevice>
        <ToSubDevice>false</ToSubDevice>
        <ToDicordTextChat>false</ToDicordTextChat>
        <Palette>Default</Palette>
      </BeforeAdvancedConfig>
      <TimeupTextToSpeak />
      <TimeupAdvancedConfig>
        <IsEnabled>false</IsEnabled>
        <ToMainDevice>true</ToMainDevice>
        <ToSubDevice>false</ToSubDevice>
        <ToDicordTextChat>false</ToDicordTextChat>
        <Palette>Default</Palette>
      </TimeupAdvancedConfig>
      <MatchSound />
      <OverSound />
      <BeforeSound />
      <TimeupSound />
    </SpellTimer>
    <SpellTimer>
      <SortPriority>0</SortPriority>
      <IsChecked>false</IsChecked>
      <IsExpanded>false</IsExpanded>
      <Enabled>true</Enabled>
      <IsCircleStyle>false</IsCircleStyle>
      <TitleVerticalAlignmentInCircle>Center</TitleVerticalAlignmentInCircle>
      <Left>0</Left>
      <Top>0</Top>
      <ID>247</ID>
      <Guid>86925a6d-4e90-4dcf-be3b-a84d52fd12ee</Guid>
      <PanelID>682207e0-c8bb-40ee-9f5a-687041c092fd</PanelID>
      <Panel>シナジースキル効果時間表示</Panel>
      <SpellTitle>戦士のリプ</SpellTitle>
      <RegexEnabled>true</RegexEnabled>
      <Keyword>^00:&lt;id4&gt;:&lt;2ex&gt;の「リプライザル」$</Keyword>
      <KeywordForExtend1 />
      <KeywordForExtend2 />
      <RecastTime>60</RecastTime>
      <DelayToShow>0</DelayToShow>
      <RecastTimeExtending1>0</RecastTimeExtending1>
      <RecastTimeExtending2>0</RecastTimeExtending2>
      <RecastTimeExtending3>0</RecastTimeExtending3>
      <OverlapRecastTime>true</OverlapRecastTime>
      <IsNotResetBarOnExtended>false</IsNotResetBarOnExtended>
      <ProgressBarVisible>false</ProgressBarVisible>
      <Font FontFamily="Impact" Size="14" Stretch="Condensed" Style="Normal" Weight="Normal" />
      <FontColor>#FFFFFF</FontColor>
      <FontOutlineColor>#696969</FontOutlineColor>
      <WarningTime>0</WarningTime>
      <ChangeFontColorsWhenWarning>false</ChangeFontColorsWhenWarning>
      <WarningFontColor>#FFFFFF</WarningFontColor>
      <WarningFontOutlineColor>#FF4500</WarningFontOutlineColor>
      <ChangeFontColorWhenContainsMe>false</ChangeFontColorWhenContainsMe>
      <BarWidth>35</BarWidth>
      <BarHeight>3</BarHeight>
      <BarColor>#FFFFFF</BarColor>
      <BarOutlineColor>#191970</BarOutlineColor>
      <BarBlurRadius>0</BarBlurRadius>
      <BackgroundColor>#FFFFFF</BackgroundColor>
      <BackgroundAlpha>0</BackgroundAlpha>
      <DisplayNo>1104</DisplayNo>
      <DontHide>false</DontHide>
      <IsHideInNotCombat>false</IsHideInNotCombat>
      <ExtendBeyondOriginalRecastTime>false</ExtendBeyondOriginalRecastTime>
      <HideSpellName>false</HideSpellName>
      <HideCounter>false</HideCounter>
      <IsCounterToCenter>false</IsCounterToCenter>
      <IsReverse>false</IsReverse>
      <MatchDateTime>0001-01-01T00:00:00</MatchDateTime>
      <UseHotbarRecastTime>false</UseHotbarRecastTime>
      <HotbarName />
      <ReduceIconBrightness>true</ReduceIconBrightness>
      <SpellIcon>7535_リプライザル.png</SpellIcon>
      <SpellIconSize>29</SpellIconSize>
      <IsNotResetAtWipeout>false</IsNotResetAtWipeout>
      <TimeupHide>false</TimeupHide>
      <ToInstance>false</ToInstance>
      <UpperLimitOfExtension>0</UpperLimitOfExtension>
      <BlinkTime>0</BlinkTime>
      <BlinkIcon>false</BlinkIcon>
      <BlinkBar>false</BlinkBar>
      <JobFilter />
      <PartyJobFilter>3,21</PartyJobFilter>
      <PartyCompositionFilter />
      <ZoneFilter />
      <TimersMustRunningForStart />
      <TimersMustStoppingForStart />
      <ExpressionFilter>
        <expression />
        <expression />
        <expression />
        <expression />
      </ExpressionFilter>
      <IsSequentialTTS>false</IsSequentialTTS>
      <MatchTextToSpeak>戦士のリプ</MatchTextToSpeak>
      <MatchAdvancedConfig>
        <IsEnabled>false</IsEnabled>
        <ToMainDevice>true</ToMainDevice>
        <ToSubDevice>false</ToSubDevice>
        <ToDicordTextChat>false</ToDicordTextChat>
        <Palette>Default</Palette>
      </MatchAdvancedConfig>
      <OverTime>0</OverTime>
      <OverTextToSpeak />
      <OverAdvancedConfig>
        <IsEnabled>false</IsEnabled>
        <ToMainDevice>true</ToMainDevice>
        <ToSubDevice>false</ToSubDevice>
        <ToDicordTextChat>false</ToDicordTextChat>
        <Palette>Default</Palette>
      </OverAdvancedConfig>
      <BeforeTime>0</BeforeTime>
      <BeforeTextToSpeak />
      <BeforeAdvancedConfig>
        <IsEnabled>false</IsEnabled>
        <ToMainDevice>true</ToMainDevice>
        <ToSubDevice>false</ToSubDevice>
        <ToDicordTextChat>false</ToDicordTextChat>
        <Palette>Default</Palette>
      </BeforeAdvancedConfig>
      <TimeupTextToSpeak />
      <TimeupAdvancedConfig>
        <IsEnabled>false</IsEnabled>
        <ToMainDevice>true</ToMainDevice>
        <ToSubDevice>false</ToSubDevice>
        <ToDicordTextChat>false</ToDicordTextChat>
        <Palette>Default</Palette>
      </TimeupAdvancedConfig>
      <MatchSound />
      <OverSound />
      <BeforeSound />
      <TimeupSound />
    </SpellTimer>
    <SpellTimer>
      <SortPriority>0</SortPriority>
      <IsChecked>false</IsChecked>
      <IsExpanded>false</IsExpanded>
      <Enabled>true</Enabled>
      <IsCircleStyle>false</IsCircleStyle>
      <TitleVerticalAlignmentInCircle>Center</TitleVerticalAlignmentInCircle>
      <Left>0</Left>
      <Top>0</Top>
      <ID>248</ID>
      <Guid>cf3c08d2-8e79-401c-b378-4f0a21ce0355</Guid>
      <PanelID>682207e0-c8bb-40ee-9f5a-687041c092fd</PanelID>
      <Panel>シナジースキル効果時間表示</Panel>
      <SpellTitle>暗黒のリプ</SpellTitle>
      <RegexEnabled>true</RegexEnabled>
      <Keyword>^00:&lt;id4&gt;:&lt;2ex&gt;の「リプライザル」$</Keyword>
      <KeywordForExtend1 />
      <KeywordForExtend2 />
      <RecastTime>60</RecastTime>
      <DelayToShow>0</DelayToShow>
      <RecastTimeExtending1>0</RecastTimeExtending1>
      <RecastTimeExtending2>0</RecastTimeExtending2>
      <RecastTimeExtending3>0</RecastTimeExtending3>
      <OverlapRecastTime>true</OverlapRecastTime>
      <IsNotResetBarOnExtended>false</IsNotResetBarOnExtended>
      <ProgressBarVisible>false</ProgressBarVisible>
      <Font FontFamily="Impact" Size="14" Stretch="Condensed" Style="Normal" Weight="Normal" />
      <FontColor>#FFFFFF</FontColor>
      <FontOutlineColor>#696969</FontOutlineColor>
      <WarningTime>0</WarningTime>
      <ChangeFontColorsWhenWarning>false</ChangeFontColorsWhenWarning>
      <WarningFontColor>#FFFFFF</WarningFontColor>
      <WarningFontOutlineColor>#FF4500</WarningFontOutlineColor>
      <ChangeFontColorWhenContainsMe>false</ChangeFontColorWhenContainsMe>
      <BarWidth>35</BarWidth>
      <BarHeight>3</BarHeight>
      <BarColor>#FFFFFF</BarColor>
      <BarOutlineColor>#191970</BarOutlineColor>
      <BarBlurRadius>0</BarBlurRadius>
      <BackgroundColor>#FFFFFF</BackgroundColor>
      <BackgroundAlpha>0</BackgroundAlpha>
      <DisplayNo>1105</DisplayNo>
      <DontHide>false</DontHide>
      <IsHideInNotCombat>false</IsHideInNotCombat>
      <ExtendBeyondOriginalRecastTime>false</ExtendBeyondOriginalRecastTime>
      <HideSpellName>false</HideSpellName>
      <HideCounter>false</HideCounter>
      <IsCounterToCenter>false</IsCounterToCenter>
      <IsReverse>false</IsReverse>
      <MatchDateTime>0001-01-01T00:00:00</MatchDateTime>
      <UseHotbarRecastTime>false</UseHotbarRecastTime>
      <HotbarName />
      <ReduceIconBrightness>true</ReduceIconBrightness>
      <SpellIcon>7535_リプライザル.png</SpellIcon>
      <SpellIconSize>29</SpellIconSize>
      <IsNotResetAtWipeout>false</IsNotResetAtWipeout>
      <TimeupHide>false</TimeupHide>
      <ToInstance>false</ToInstance>
      <UpperLimitOfExtension>0</UpperLimitOfExtension>
      <BlinkTime>0</BlinkTime>
      <BlinkIcon>false</BlinkIcon>
      <BlinkBar>false</BlinkBar>
      <JobFilter />
      <PartyJobFilter>32</PartyJobFilter>
      <PartyCompositionFilter />
      <ZoneFilter />
      <TimersMustRunningForStart />
      <TimersMustStoppingForStart />
      <ExpressionFilter>
        <expression />
        <expression />
        <expression />
        <expression />
      </ExpressionFilter>
      <IsSequentialTTS>false</IsSequentialTTS>
      <MatchTextToSpeak>暗黒のリプ</MatchTextToSpeak>
      <MatchAdvancedConfig>
        <IsEnabled>false</IsEnabled>
        <ToMainDevice>true</ToMainDevice>
        <ToSubDevice>false</ToSubDevice>
        <ToDicordTextChat>false</ToDicordTextChat>
        <Palette>Default</Palette>
      </MatchAdvancedConfig>
      <OverTime>0</OverTime>
      <OverTextToSpeak />
      <OverAdvancedConfig>
        <IsEnabled>false</IsEnabled>
        <ToMainDevice>true</ToMainDevice>
        <ToSubDevice>false</ToSubDevice>
        <ToDicordTextChat>false</ToDicordTextChat>
        <Palette>Default</Palette>
      </OverAdvancedConfig>
      <BeforeTime>0</BeforeTime>
      <BeforeTextToSpeak />
      <BeforeAdvancedConfig>
        <IsEnabled>false</IsEnabled>
        <ToMainDevice>true</ToMainDevice>
        <ToSubDevice>false</ToSubDevice>
        <ToDicordTextChat>false</ToDicordTextChat>
        <Palette>Default</Palette>
      </BeforeAdvancedConfig>
      <TimeupTextToSpeak />
      <TimeupAdvancedConfig>
        <IsEnabled>false</IsEnabled>
        <ToMainDevice>true</ToMainDevice>
        <ToSubDevice>false</ToSubDevice>
        <ToDicordTextChat>false</ToDicordTextChat>
        <Palette>Default</Palette>
      </TimeupAdvancedConfig>
      <MatchSound />
      <OverSound />
      <BeforeSound />
      <TimeupSound />
    </SpellTimer>
    <SpellTimer>
      <SortPriority>0</SortPriority>
      <IsChecked>false</IsChecked>
      <IsExpanded>false</IsExpanded>
      <Enabled>true</Enabled>
      <IsCircleStyle>false</IsCircleStyle>
      <TitleVerticalAlignmentInCircle>Center</TitleVerticalAlignmentInCircle>
      <Left>0</Left>
      <Top>0</Top>
      <ID>249</ID>
      <Guid>5f49d1cd-c599-4148-b283-0fe3b536ee3c</Guid>
      <PanelID>682207e0-c8bb-40ee-9f5a-687041c092fd</PanelID>
      <Panel>シナジースキル効果時間表示</Panel>
      <SpellTitle>ガンブレのリプ</SpellTitle>
      <RegexEnabled>true</RegexEnabled>
      <Keyword>^00:&lt;id4&gt;:&lt;2ex&gt;の「リプライザル」$</Keyword>
      <KeywordForExtend1 />
      <KeywordForExtend2 />
      <RecastTime>60</RecastTime>
      <DelayToShow>0</DelayToShow>
      <RecastTimeExtending1>0</RecastTimeExtending1>
      <RecastTimeExtending2>0</RecastTimeExtending2>
      <RecastTimeExtending3>0</RecastTimeExtending3>
      <OverlapRecastTime>true</OverlapRecastTime>
      <IsNotResetBarOnExtended>false</IsNotResetBarOnExtended>
      <ProgressBarVisible>false</ProgressBarVisible>
      <Font FontFamily="Impact" Size="14" Stretch="Condensed" Style="Normal" Weight="Normal" />
      <FontColor>#FFFFFF</FontColor>
      <FontOutlineColor>#696969</FontOutlineColor>
      <WarningTime>0</WarningTime>
      <ChangeFontColorsWhenWarning>false</ChangeFontColorsWhenWarning>
      <WarningFontColor>#FFFFFF</WarningFontColor>
      <WarningFontOutlineColor>#FF4500</WarningFontOutlineColor>
      <ChangeFontColorWhenContainsMe>false</ChangeFontColorWhenContainsMe>
      <BarWidth>35</BarWidth>
      <BarHeight>3</BarHeight>
      <BarColor>#FFFFFF</BarColor>
      <BarOutlineColor>#191970</BarOutlineColor>
      <BarBlurRadius>0</BarBlurRadius>
      <BackgroundColor>#FFFFFF</BackgroundColor>
      <BackgroundAlpha>0</BackgroundAlpha>
      <DisplayNo>1106</DisplayNo>
      <DontHide>false</DontHide>
      <IsHideInNotCombat>false</IsHideInNotCombat>
      <ExtendBeyondOriginalRecastTime>false</ExtendBeyondOriginalRecastTime>
      <HideSpellName>false</HideSpellName>
      <HideCounter>false</HideCounter>
      <IsCounterToCenter>false</IsCounterToCenter>
      <IsReverse>false</IsReverse>
      <MatchDateTime>0001-01-01T00:00:00</MatchDateTime>
      <UseHotbarRecastTime>false</UseHotbarRecastTime>
      <HotbarName />
      <ReduceIconBrightness>true</ReduceIconBrightness>
      <SpellIcon>7535_リプライザル.png</SpellIcon>
      <SpellIconSize>29</SpellIconSize>
      <IsNotResetAtWipeout>false</IsNotResetAtWipeout>
      <TimeupHide>false</TimeupHide>
      <ToInstance>false</ToInstance>
      <UpperLimitOfExtension>0</UpperLimitOfExtension>
      <BlinkTime>0</BlinkTime>
      <BlinkIcon>false</BlinkIcon>
      <BlinkBar>false</BlinkBar>
      <JobFilter />
      <PartyJobFilter>37</PartyJobFilter>
      <PartyCompositionFilter />
      <ZoneFilter />
      <TimersMustRunningForStart />
      <TimersMustStoppingForStart />
      <ExpressionFilter>
        <expression />
        <expression />
        <expression />
        <expression />
      </ExpressionFilter>
      <IsSequentialTTS>false</IsSequentialTTS>
      <MatchTextToSpeak>ガンブレのリプ</MatchTextToSpeak>
      <MatchAdvancedConfig>
        <IsEnabled>false</IsEnabled>
        <ToMainDevice>true</ToMainDevice>
        <ToSubDevice>false</ToSubDevice>
        <ToDicordTextChat>false</ToDicordTextChat>
        <Palette>Default</Palette>
      </MatchAdvancedConfig>
      <OverTime>0</OverTime>
      <OverTextToSpeak />
      <OverAdvancedConfig>
        <IsEnabled>false</IsEnabled>
        <ToMainDevice>true</ToMainDevice>
        <ToSubDevice>false</ToSubDevice>
        <ToDicordTextChat>false</ToDicordTextChat>
        <Palette>Default</Palette>
      </OverAdvancedConfig>
      <BeforeTime>0</BeforeTime>
      <BeforeTextToSpeak />
      <BeforeAdvancedConfig>
        <IsEnabled>false</IsEnabled>
        <ToMainDevice>true</ToMainDevice>
        <ToSubDevice>false</ToSubDevice>
        <ToDicordTextChat>false</ToDicordTextChat>
        <Palette>Default</Palette>
      </BeforeAdvancedConfig>
      <TimeupTextToSpeak />
      <TimeupAdvancedConfig>
        <IsEnabled>false</IsEnabled>
        <ToMainDevice>true</ToMainDevice>
        <ToSubDevice>false</ToSubDevice>
        <ToDicordTextChat>false</ToDicordTextChat>
        <Palette>Default</Palette>
      </TimeupAdvancedConfig>
      <MatchSound />
      <OverSound />
      <BeforeSound />
      <TimeupSound />
    </SpellTimer>
    <SpellTimer>
      <SortPriority>0</SortPriority>
      <IsChecked>false</IsChecked>
      <IsExpanded>false</IsExpanded>
      <Enabled>false</Enabled>
      <IsCircleStyle>true</IsCircleStyle>
      <TitleVerticalAlignmentInCircle>Center</TitleVerticalAlignmentInCircle>
      <Left>0</Left>
      <Top>0</Top>
      <ID>15</ID>
      <Guid>265c96a6-a09e-41ba-b169-543af37f9ee0</Guid>
      <PanelID>682207e0-c8bb-40ee-9f5a-687041c092fd</PanelID>
      <Panel>シナジースキル効果時間表示</Panel>
      <SpellTitle>ディヴィネーション：効果</SpellTitle>
      <RegexEnabled>true</RegexEnabled>
      <Keyword>&lt;mex&gt; gains the effect of ディヴィネーション</Keyword>
      <KeywordForExtend1 />
      <KeywordForExtend2 />
      <RecastTime>120</RecastTime>
      <DelayToShow>0</DelayToShow>
      <RecastTimeExtending1>0</RecastTimeExtending1>
      <RecastTimeExtending2>0</RecastTimeExtending2>
      <RecastTimeExtending3>0</RecastTimeExtending3>
      <OverlapRecastTime>true</OverlapRecastTime>
      <IsNotResetBarOnExtended>false</IsNotResetBarOnExtended>
      <ProgressBarVisible>true</ProgressBarVisible>
      <Font FontFamily="Impact" Size="13" Stretch="Condensed" Style="Normal" Weight="Normal" />
      <FontColor>#FFFFFF</FontColor>
      <FontOutlineColor>#0000FF</FontOutlineColor>
      <WarningTime>3</WarningTime>
      <ChangeFontColorsWhenWarning>true</ChangeFontColorsWhenWarning>
      <WarningFontColor>Transparent</WarningFontColor>
      <WarningFontOutlineColor>Transparent</WarningFontOutlineColor>
      <ChangeFontColorWhenContainsMe>false</ChangeFontColorWhenContainsMe>
      <BarWidth>35</BarWidth>
      <BarHeight>3</BarHeight>
      <BarColor>#FEF263</BarColor>
      <BarOutlineColor>#000000</BarOutlineColor>
      <BarBlurRadius>15</BarBlurRadius>
      <BackgroundColor>#FFFFFF</BackgroundColor>
      <BackgroundAlpha>0</BackgroundAlpha>
      <DisplayNo>1107</DisplayNo>
      <DontHide>false</DontHide>
      <IsHideInNotCombat>false</IsHideInNotCombat>
      <ExtendBeyondOriginalRecastTime>false</ExtendBeyondOriginalRecastTime>
      <HideSpellName>true</HideSpellName>
      <HideCounter>false</HideCounter>
      <IsCounterToCenter>false</IsCounterToCenter>
      <IsReverse>true</IsReverse>
      <MatchDateTime>0001-01-01T00:00:00</MatchDateTime>
      <UseHotbarRecastTime>false</UseHotbarRecastTime>
      <HotbarName />
      <ReduceIconBrightness>true</ReduceIconBrightness>
      <SpellIcon>16552_ディヴィネーション.png</SpellIcon>
      <SpellIconSize>29</SpellIconSize>
      <IsNotResetAtWipeout>false</IsNotResetAtWipeout>
      <TimeupHide>false</TimeupHide>
      <ToInstance>true</ToInstance>
      <UpperLimitOfExtension>0</UpperLimitOfExtension>
      <BlinkTime>0</BlinkTime>
      <BlinkIcon>false</BlinkIcon>
      <BlinkBar>false</BlinkBar>
      <JobFilter />
      <PartyJobFilter>33</PartyJobFilter>
      <PartyCompositionFilter>LightParty,FullPartyT1,FullPartyT2</PartyCompositionFilter>
      <ZoneFilter />
      <TimersMustRunningForStart />
      <TimersMustStoppingForStart />
      <ExpressionFilter>
        <expression />
        <expression />
        <expression />
        <expression />
      </ExpressionFilter>
      <IsSequentialTTS>false</IsSequentialTTS>
      <MatchTextToSpeak />
      <MatchAdvancedConfig>
        <IsEnabled>false</IsEnabled>
        <ToMainDevice>true</ToMainDevice>
        <ToSubDevice>false</ToSubDevice>
        <ToDicordTextChat>false</ToDicordTextChat>
        <Palette>Default</Palette>
      </MatchAdvancedConfig>
      <OverTime>0</OverTime>
      <OverTextToSpeak />
      <OverAdvancedConfig>
        <IsEnabled>false</IsEnabled>
        <ToMainDevice>true</ToMainDevice>
        <ToSubDevice>false</ToSubDevice>
        <ToDicordTextChat>false</ToDicordTextChat>
        <Palette>Default</Palette>
      </OverAdvancedConfig>
      <BeforeTime>0</BeforeTime>
      <BeforeTextToSpeak />
      <BeforeAdvancedConfig>
        <IsEnabled>false</IsEnabled>
        <ToMainDevice>true</ToMainDevice>
        <ToSubDevice>false</ToSubDevice>
        <ToDicordTextChat>false</ToDicordTextChat>
        <Palette>Default</Palette>
      </BeforeAdvancedConfig>
      <TimeupTextToSpeak />
      <TimeupAdvancedConfig>
        <IsEnabled>false</IsEnabled>
        <ToMainDevice>true</ToMainDevice>
        <ToSubDevice>false</ToSubDevice>
        <ToDicordTextChat>false</ToDicordTextChat>
        <Palette>Default</Palette>
      </TimeupAdvancedConfig>
      <MatchSound />
      <OverSound />
      <BeforeSound />
      <TimeupSound />
    </SpellTimer>
    <SpellTimer>
      <SortPriority>0</SortPriority>
      <IsChecked>false</IsChecked>
      <IsExpanded>false</IsExpanded>
      <Enabled>false</Enabled>
      <IsCircleStyle>true</IsCircleStyle>
      <TitleVerticalAlignmentInCircle>Center</TitleVerticalAlignmentInCircle>
      <Left>0</Left>
      <Top>0</Top>
      <ID>20</ID>
      <Guid>f4400003-f2e1-4595-8af7-9633473f58ed</Guid>
      <PanelID>682207e0-c8bb-40ee-9f5a-687041c092fd</PanelID>
      <Panel>シナジースキル効果時間表示</Panel>
      <SpellTitle>ドラゴンサイト：効果</SpellTitle>
      <RegexEnabled>true</RegexEnabled>
      <Keyword>&lt;mex&gt; gains the effect of 竜の(左|右)眼</Keyword>
      <KeywordForExtend1 />
      <KeywordForExtend2 />
      <RecastTime>120</RecastTime>
      <DelayToShow>0</DelayToShow>
      <RecastTimeExtending1>0</RecastTimeExtending1>
      <RecastTimeExtending2>0</RecastTimeExtending2>
      <RecastTimeExtending3>0</RecastTimeExtending3>
      <OverlapRecastTime>true</OverlapRecastTime>
      <IsNotResetBarOnExtended>false</IsNotResetBarOnExtended>
      <ProgressBarVisible>true</ProgressBarVisible>
      <Font FontFamily="Impact" Size="13" Stretch="Condensed" Style="Normal" Weight="Normal" />
      <FontColor>#FFFFFF</FontColor>
      <FontOutlineColor>#0000FF</FontOutlineColor>
      <WarningTime>3</WarningTime>
      <ChangeFontColorsWhenWarning>true</ChangeFontColorsWhenWarning>
      <WarningFontColor>Transparent</WarningFontColor>
      <WarningFontOutlineColor>Transparent</WarningFontOutlineColor>
      <ChangeFontColorWhenContainsMe>false</ChangeFontColorWhenContainsMe>
      <BarWidth>35</BarWidth>
      <BarHeight>3</BarHeight>
      <BarColor>#FEF263</BarColor>
      <BarOutlineColor>#000000</BarOutlineColor>
      <BarBlurRadius>15</BarBlurRadius>
      <BackgroundColor>#FFFFFF</BackgroundColor>
      <BackgroundAlpha>0</BackgroundAlpha>
      <DisplayNo>1108</DisplayNo>
      <DontHide>false</DontHide>
      <IsHideInNotCombat>false</IsHideInNotCombat>
      <ExtendBeyondOriginalRecastTime>false</ExtendBeyondOriginalRecastTime>
      <HideSpellName>true</HideSpellName>
      <HideCounter>false</HideCounter>
      <IsCounterToCenter>false</IsCounterToCenter>
      <IsReverse>true</IsReverse>
      <MatchDateTime>0001-01-01T00:00:00</MatchDateTime>
      <UseHotbarRecastTime>false</UseHotbarRecastTime>
      <HotbarName />
      <ReduceIconBrightness>true</ReduceIconBrightness>
      <SpellIcon>7398_ドラゴンサイト.png</SpellIcon>
      <SpellIconSize>29</SpellIconSize>
      <IsNotResetAtWipeout>false</IsNotResetAtWipeout>
      <TimeupHide>false</TimeupHide>
      <ToInstance>true</ToInstance>
      <UpperLimitOfExtension>0</UpperLimitOfExtension>
      <BlinkTime>0</BlinkTime>
      <BlinkIcon>false</BlinkIcon>
      <BlinkBar>false</BlinkBar>
      <JobFilter />
      <PartyJobFilter>22</PartyJobFilter>
      <PartyCompositionFilter>LightParty,FullPartyT1,FullPartyT2</PartyCompositionFilter>
      <ZoneFilter />
      <TimersMustRunningForStart />
      <TimersMustStoppingForStart />
      <ExpressionFilter>
        <expression />
        <expression />
        <expression />
        <expression />
      </ExpressionFilter>
      <IsSequentialTTS>false</IsSequentialTTS>
      <MatchTextToSpeak />
      <MatchAdvancedConfig>
        <IsEnabled>false</IsEnabled>
        <ToMainDevice>true</ToMainDevice>
        <ToSubDevice>false</ToSubDevice>
        <ToDicordTextChat>false</ToDicordTextChat>
        <Palette>Default</Palette>
      </MatchAdvancedConfig>
      <OverTime>0</OverTime>
      <OverTextToSpeak />
      <OverAdvancedConfig>
        <IsEnabled>false</IsEnabled>
        <ToMainDevice>true</ToMainDevice>
        <ToSubDevice>false</ToSubDevice>
        <ToDicordTextChat>false</ToDicordTextChat>
        <Palette>Default</Palette>
      </OverAdvancedConfig>
      <BeforeTime>5</BeforeTime>
      <BeforeTextToSpeak />
      <BeforeAdvancedConfig>
        <IsEnabled>false</IsEnabled>
        <ToMainDevice>true</ToMainDevice>
        <ToSubDevice>false</ToSubDevice>
        <ToDicordTextChat>false</ToDicordTextChat>
        <Palette>Default</Palette>
      </BeforeAdvancedConfig>
      <TimeupTextToSpeak />
      <TimeupAdvancedConfig>
        <IsEnabled>false</IsEnabled>
        <ToMainDevice>true</ToMainDevice>
        <ToSubDevice>false</ToSubDevice>
        <ToDicordTextChat>false</ToDicordTextChat>
        <Palette>Default</Palette>
      </TimeupAdvancedConfig>
      <MatchSound />
      <OverSound />
      <BeforeSound>_beep.wav</BeforeSound>
      <TimeupSound />
    </SpellTimer>
    <SpellTimer>
      <SortPriority>0</SortPriority>
      <IsChecked>false</IsChecked>
      <IsExpanded>false</IsExpanded>
      <Enabled>false</Enabled>
      <IsCircleStyle>true</IsCircleStyle>
      <TitleVerticalAlignmentInCircle>Center</TitleVerticalAlignmentInCircle>
      <Left>0</Left>
      <Top>0</Top>
      <ID>16</ID>
      <Guid>81be79aa-701d-4e56-aa48-0c9a2d6985f7</Guid>
      <PanelID>682207e0-c8bb-40ee-9f5a-687041c092fd</PanelID>
      <Panel>シナジースキル効果時間表示</Panel>
      <SpellTitle>攻めのタンゴ：効果</SpellTitle>
      <RegexEnabled>true</RegexEnabled>
      <Keyword>&lt;mex&gt; gains the effect of 攻めのタンゴ</Keyword>
      <KeywordForExtend1 />
      <KeywordForExtend2 />
      <RecastTime>120</RecastTime>
      <DelayToShow>0</DelayToShow>
      <RecastTimeExtending1>0</RecastTimeExtending1>
      <RecastTimeExtending2>0</RecastTimeExtending2>
      <RecastTimeExtending3>0</RecastTimeExtending3>
      <OverlapRecastTime>true</OverlapRecastTime>
      <IsNotResetBarOnExtended>false</IsNotResetBarOnExtended>
      <ProgressBarVisible>true</ProgressBarVisible>
      <Font FontFamily="Impact" Size="13" Stretch="Condensed" Style="Normal" Weight="Normal" />
      <FontColor>#FFFFFF</FontColor>
      <FontOutlineColor>#0000FF</FontOutlineColor>
      <WarningTime>3</WarningTime>
      <ChangeFontColorsWhenWarning>true</ChangeFontColorsWhenWarning>
      <WarningFontColor>Transparent</WarningFontColor>
      <WarningFontOutlineColor>Transparent</WarningFontOutlineColor>
      <ChangeFontColorWhenContainsMe>false</ChangeFontColorWhenContainsMe>
      <BarWidth>35</BarWidth>
      <BarHeight>3</BarHeight>
      <BarColor>#FEF263</BarColor>
      <BarOutlineColor>#000000</BarOutlineColor>
      <BarBlurRadius>15</BarBlurRadius>
      <BackgroundColor>#FFFFFF</BackgroundColor>
      <BackgroundAlpha>0</BackgroundAlpha>
      <DisplayNo>1109</DisplayNo>
      <DontHide>false</DontHide>
      <IsHideInNotCombat>false</IsHideInNotCombat>
      <ExtendBeyondOriginalRecastTime>false</ExtendBeyondOriginalRecastTime>
      <HideSpellName>true</HideSpellName>
      <HideCounter>false</HideCounter>
      <IsCounterToCenter>false</IsCounterToCenter>
      <IsReverse>true</IsReverse>
      <MatchDateTime>0001-01-01T00:00:00</MatchDateTime>
      <UseHotbarRecastTime>false</UseHotbarRecastTime>
      <HotbarName />
      <ReduceIconBrightness>true</ReduceIconBrightness>
      <SpellIcon>16011_攻めのタンゴ.png</SpellIcon>
      <SpellIconSize>29</SpellIconSize>
      <IsNotResetAtWipeout>false</IsNotResetAtWipeout>
      <TimeupHide>false</TimeupHide>
      <ToInstance>true</ToInstance>
      <UpperLimitOfExtension>0</UpperLimitOfExtension>
      <BlinkTime>0</BlinkTime>
      <BlinkIcon>false</BlinkIcon>
      <BlinkBar>false</BlinkBar>
      <JobFilter />
      <PartyJobFilter>38</PartyJobFilter>
      <PartyCompositionFilter>LightParty,FullPartyT1,FullPartyT2</PartyCompositionFilter>
      <ZoneFilter />
      <TimersMustRunningForStart />
      <TimersMustStoppingForStart />
      <ExpressionFilter>
        <expression />
        <expression />
        <expression />
        <expression />
      </ExpressionFilter>
      <IsSequentialTTS>false</IsSequentialTTS>
      <MatchTextToSpeak />
      <MatchAdvancedConfig>
        <IsEnabled>false</IsEnabled>
        <ToMainDevice>true</ToMainDevice>
        <ToSubDevice>false</ToSubDevice>
        <ToDicordTextChat>false</ToDicordTextChat>
        <Palette>Default</Palette>
      </MatchAdvancedConfig>
      <OverTime>0</OverTime>
      <OverTextToSpeak />
      <OverAdvancedConfig>
        <IsEnabled>false</IsEnabled>
        <ToMainDevice>true</ToMainDevice>
        <ToSubDevice>false</ToSubDevice>
        <ToDicordTextChat>false</ToDicordTextChat>
        <Palette>Default</Palette>
      </OverAdvancedConfig>
      <BeforeTime>0</BeforeTime>
      <BeforeTextToSpeak />
      <BeforeAdvancedConfig>
        <IsEnabled>false</IsEnabled>
        <ToMainDevice>true</ToMainDevice>
        <ToSubDevice>false</ToSubDevice>
        <ToDicordTextChat>false</ToDicordTextChat>
        <Palette>Default</Palette>
      </BeforeAdvancedConfig>
      <TimeupTextToSpeak />
      <TimeupAdvancedConfig>
        <IsEnabled>false</IsEnabled>
        <ToMainDevice>true</ToMainDevice>
        <ToSubDevice>false</ToSubDevice>
        <ToDicordTextChat>false</ToDicordTextChat>
        <Palette>Default</Palette>
      </TimeupAdvancedConfig>
      <MatchSound />
      <OverSound />
      <BeforeSound />
      <TimeupSound />
    </SpellTimer>
    <SpellTimer>
      <SortPriority>0</SortPriority>
      <IsChecked>false</IsChecked>
      <IsExpanded>false</IsExpanded>
      <Enabled>false</Enabled>
      <IsCircleStyle>true</IsCircleStyle>
      <TitleVerticalAlignmentInCircle>Center</TitleVerticalAlignmentInCircle>
      <Left>0</Left>
      <Top>0</Top>
      <ID>17</ID>
      <Guid>3190423b-cddc-440e-b915-a6c52f1fd3f4</Guid>
      <PanelID>682207e0-c8bb-40ee-9f5a-687041c092fd</PanelID>
      <Panel>シナジースキル効果時間表示</Panel>
      <SpellTitle>テクニカルフィニッシュ：効果</SpellTitle>
      <RegexEnabled>true</RegexEnabled>
      <Keyword>&lt;mex&gt; gains the effect of テクニカルフィニッシュ</Keyword>
      <KeywordForExtend1 />
      <KeywordForExtend2 />
      <RecastTime>120</RecastTime>
      <DelayToShow>0</DelayToShow>
      <RecastTimeExtending1>0</RecastTimeExtending1>
      <RecastTimeExtending2>0</RecastTimeExtending2>
      <RecastTimeExtending3>0</RecastTimeExtending3>
      <OverlapRecastTime>true</OverlapRecastTime>
      <IsNotResetBarOnExtended>false</IsNotResetBarOnExtended>
      <ProgressBarVisible>true</ProgressBarVisible>
      <Font FontFamily="Impact" Size="13" Stretch="Condensed" Style="Normal" Weight="Normal" />
      <FontColor>#FFFFFF</FontColor>
      <FontOutlineColor>#0000FF</FontOutlineColor>
      <WarningTime>3</WarningTime>
      <ChangeFontColorsWhenWarning>true</ChangeFontColorsWhenWarning>
      <WarningFontColor>Transparent</WarningFontColor>
      <WarningFontOutlineColor>Transparent</WarningFontOutlineColor>
      <ChangeFontColorWhenContainsMe>false</ChangeFontColorWhenContainsMe>
      <BarWidth>35</BarWidth>
      <BarHeight>3</BarHeight>
      <BarColor>#FEF263</BarColor>
      <BarOutlineColor>#000000</BarOutlineColor>
      <BarBlurRadius>15</BarBlurRadius>
      <BackgroundColor>#FFFFFF</BackgroundColor>
      <BackgroundAlpha>0</BackgroundAlpha>
      <DisplayNo>1110</DisplayNo>
      <DontHide>false</DontHide>
      <IsHideInNotCombat>false</IsHideInNotCombat>
      <ExtendBeyondOriginalRecastTime>false</ExtendBeyondOriginalRecastTime>
      <HideSpellName>true</HideSpellName>
      <HideCounter>false</HideCounter>
      <IsCounterToCenter>false</IsCounterToCenter>
      <IsReverse>true</IsReverse>
      <MatchDateTime>0001-01-01T00:00:00</MatchDateTime>
      <UseHotbarRecastTime>false</UseHotbarRecastTime>
      <HotbarName />
      <ReduceIconBrightness>true</ReduceIconBrightness>
      <SpellIcon>16004_テクニカルフィニッシュ.png</SpellIcon>
      <SpellIconSize>29</SpellIconSize>
      <IsNotResetAtWipeout>false</IsNotResetAtWipeout>
      <TimeupHide>false</TimeupHide>
      <ToInstance>true</ToInstance>
      <UpperLimitOfExtension>0</UpperLimitOfExtension>
      <BlinkTime>0</BlinkTime>
      <BlinkIcon>false</BlinkIcon>
      <BlinkBar>false</BlinkBar>
      <JobFilter />
      <PartyJobFilter>38</PartyJobFilter>
      <PartyCompositionFilter>LightParty,FullPartyT1,FullPartyT2</PartyCompositionFilter>
      <ZoneFilter />
      <TimersMustRunningForStart />
      <TimersMustStoppingForStart />
      <ExpressionFilter>
        <expression />
        <expression />
        <expression />
        <expression />
      </ExpressionFilter>
      <IsSequentialTTS>false</IsSequentialTTS>
      <MatchTextToSpeak />
      <MatchAdvancedConfig>
        <IsEnabled>false</IsEnabled>
        <ToMainDevice>true</ToMainDevice>
        <ToSubDevice>false</ToSubDevice>
        <ToDicordTextChat>false</ToDicordTextChat>
        <Palette>Default</Palette>
      </MatchAdvancedConfig>
      <OverTime>0</OverTime>
      <OverTextToSpeak />
      <OverAdvancedConfig>
        <IsEnabled>false</IsEnabled>
        <ToMainDevice>true</ToMainDevice>
        <ToSubDevice>false</ToSubDevice>
        <ToDicordTextChat>false</ToDicordTextChat>
        <Palette>Default</Palette>
      </OverAdvancedConfig>
      <BeforeTime>0</BeforeTime>
      <BeforeTextToSpeak />
      <BeforeAdvancedConfig>
        <IsEnabled>false</IsEnabled>
        <ToMainDevice>true</ToMainDevice>
        <ToSubDevice>false</ToSubDevice>
        <ToDicordTextChat>false</ToDicordTextChat>
        <Palette>Default</Palette>
      </BeforeAdvancedConfig>
      <TimeupTextToSpeak />
      <TimeupAdvancedConfig>
        <IsEnabled>false</IsEnabled>
        <ToMainDevice>true</ToMainDevice>
        <ToSubDevice>false</ToSubDevice>
        <ToDicordTextChat>false</ToDicordTextChat>
        <Palette>Default</Palette>
      </TimeupAdvancedConfig>
      <MatchSound />
      <OverSound />
      <BeforeSound />
      <TimeupSound />
    </SpellTimer>
    <SpellTimer>
      <SortPriority>0</SortPriority>
      <IsChecked>false</IsChecked>
      <IsExpanded>false</IsExpanded>
      <Enabled>false</Enabled>
      <IsCircleStyle>true</IsCircleStyle>
      <TitleVerticalAlignmentInCircle>Center</TitleVerticalAlignmentInCircle>
      <Left>0</Left>
      <Top>0</Top>
      <ID>19</ID>
      <Guid>d570af74-40f0-4c2d-b289-4079c58b3009</Guid>
      <PanelID>682207e0-c8bb-40ee-9f5a-687041c092fd</PanelID>
      <Panel>シナジースキル効果時間表示</Panel>
      <SpellTitle>エギの加護：効果</SpellTitle>
      <RegexEnabled>true</RegexEnabled>
      <Keyword>&lt;mex&gt; gains the effect of エギの加護</Keyword>
      <KeywordForExtend1 />
      <KeywordForExtend2 />
      <RecastTime>180</RecastTime>
      <DelayToShow>0</DelayToShow>
      <RecastTimeExtending1>0</RecastTimeExtending1>
      <RecastTimeExtending2>0</RecastTimeExtending2>
      <RecastTimeExtending3>0</RecastTimeExtending3>
      <OverlapRecastTime>true</OverlapRecastTime>
      <IsNotResetBarOnExtended>false</IsNotResetBarOnExtended>
      <ProgressBarVisible>true</ProgressBarVisible>
      <Font FontFamily="Impact" Size="13" Stretch="Condensed" Style="Normal" Weight="Normal" />
      <FontColor>#FFFFFF</FontColor>
      <FontOutlineColor>#0000FF</FontOutlineColor>
      <WarningTime>3</WarningTime>
      <ChangeFontColorsWhenWarning>true</ChangeFontColorsWhenWarning>
      <WarningFontColor>Transparent</WarningFontColor>
      <WarningFontOutlineColor>Transparent</WarningFontOutlineColor>
      <ChangeFontColorWhenContainsMe>false</ChangeFontColorWhenContainsMe>
      <BarWidth>35</BarWidth>
      <BarHeight>3</BarHeight>
      <BarColor>#FEF263</BarColor>
      <BarOutlineColor>#000000</BarOutlineColor>
      <BarBlurRadius>15</BarBlurRadius>
      <BackgroundColor>#FFFFFF</BackgroundColor>
      <BackgroundAlpha>0</BackgroundAlpha>
      <DisplayNo>1111</DisplayNo>
      <DontHide>false</DontHide>
      <IsHideInNotCombat>false</IsHideInNotCombat>
      <ExtendBeyondOriginalRecastTime>false</ExtendBeyondOriginalRecastTime>
      <HideSpellName>true</HideSpellName>
      <HideCounter>false</HideCounter>
      <IsCounterToCenter>false</IsCounterToCenter>
      <IsReverse>true</IsReverse>
      <MatchDateTime>0001-01-01T00:00:00</MatchDateTime>
      <UseHotbarRecastTime>false</UseHotbarRecastTime>
      <HotbarName />
      <ReduceIconBrightness>true</ReduceIconBrightness>
      <SpellIcon>7450_エギの加護.png</SpellIcon>
      <SpellIconSize>29</SpellIconSize>
      <IsNotResetAtWipeout>false</IsNotResetAtWipeout>
      <TimeupHide>false</TimeupHide>
      <ToInstance>true</ToInstance>
      <UpperLimitOfExtension>0</UpperLimitOfExtension>
      <BlinkTime>0</BlinkTime>
      <BlinkIcon>false</BlinkIcon>
      <BlinkBar>false</BlinkBar>
      <JobFilter />
      <PartyJobFilter>27</PartyJobFilter>
      <PartyCompositionFilter>LightParty,FullPartyT1,FullPartyT2</PartyCompositionFilter>
      <ZoneFilter />
      <TimersMustRunningForStart />
      <TimersMustStoppingForStart />
      <ExpressionFilter>
        <expression />
        <expression />
        <expression />
        <expression />
      </ExpressionFilter>
      <IsSequentialTTS>false</IsSequentialTTS>
      <MatchTextToSpeak />
      <MatchAdvancedConfig>
        <IsEnabled>false</IsEnabled>
        <ToMainDevice>true</ToMainDevice>
        <ToSubDevice>false</ToSubDevice>
        <ToDicordTextChat>false</ToDicordTextChat>
        <Palette>Default</Palette>
      </MatchAdvancedConfig>
      <OverTime>0</OverTime>
      <OverTextToSpeak />
      <OverAdvancedConfig>
        <IsEnabled>false</IsEnabled>
        <ToMainDevice>true</ToMainDevice>
        <ToSubDevice>false</ToSubDevice>
        <ToDicordTextChat>false</ToDicordTextChat>
        <Palette>Default</Palette>
      </OverAdvancedConfig>
      <BeforeTime>0</BeforeTime>
      <BeforeTextToSpeak />
      <BeforeAdvancedConfig>
        <IsEnabled>false</IsEnabled>
        <ToMainDevice>true</ToMainDevice>
        <ToSubDevice>false</ToSubDevice>
        <ToDicordTextChat>false</ToDicordTextChat>
        <Palette>Default</Palette>
      </BeforeAdvancedConfig>
      <TimeupTextToSpeak />
      <TimeupAdvancedConfig>
        <IsEnabled>false</IsEnabled>
        <ToMainDevice>true</ToMainDevice>
        <ToSubDevice>false</ToSubDevice>
        <ToDicordTextChat>false</ToDicordTextChat>
        <Palette>Default</Palette>
      </TimeupAdvancedConfig>
      <MatchSound />
      <OverSound />
      <BeforeSound />
      <TimeupSound />
    </SpellTimer>
    <SpellTimer>
      <SortPriority>0</SortPriority>
      <IsChecked>false</IsChecked>
      <IsExpanded>false</IsExpanded>
      <Enabled>false</Enabled>
      <IsCircleStyle>true</IsCircleStyle>
      <TitleVerticalAlignmentInCircle>Center</TitleVerticalAlignmentInCircle>
      <Left>0</Left>
      <Top>0</Top>
      <ID>21</ID>
      <Guid>00744098-bc87-4c9e-996b-7ed078dbdfef</Guid>
      <PanelID>682207e0-c8bb-40ee-9f5a-687041c092fd</PanelID>
      <Panel>シナジースキル効果時間表示</Panel>
      <SpellTitle>バトルリタニー：効果</SpellTitle>
      <RegexEnabled>true</RegexEnabled>
      <Keyword>&lt;mex&gt; gains the effect of バトルリタニー</Keyword>
      <KeywordForExtend1 />
      <KeywordForExtend2 />
      <RecastTime>180</RecastTime>
      <DelayToShow>0</DelayToShow>
      <RecastTimeExtending1>0</RecastTimeExtending1>
      <RecastTimeExtending2>0</RecastTimeExtending2>
      <RecastTimeExtending3>0</RecastTimeExtending3>
      <OverlapRecastTime>true</OverlapRecastTime>
      <IsNotResetBarOnExtended>false</IsNotResetBarOnExtended>
      <ProgressBarVisible>true</ProgressBarVisible>
      <Font FontFamily="Impact" Size="13" Stretch="Condensed" Style="Normal" Weight="Normal" />
      <FontColor>#FFFFFF</FontColor>
      <FontOutlineColor>#0000FF</FontOutlineColor>
      <WarningTime>3</WarningTime>
      <ChangeFontColorsWhenWarning>true</ChangeFontColorsWhenWarning>
      <WarningFontColor>Transparent</WarningFontColor>
      <WarningFontOutlineColor>Transparent</WarningFontOutlineColor>
      <ChangeFontColorWhenContainsMe>false</ChangeFontColorWhenContainsMe>
      <BarWidth>35</BarWidth>
      <BarHeight>3</BarHeight>
      <BarColor>#FEF263</BarColor>
      <BarOutlineColor>#000000</BarOutlineColor>
      <BarBlurRadius>15</BarBlurRadius>
      <BackgroundColor>#FFFFFF</BackgroundColor>
      <BackgroundAlpha>0</BackgroundAlpha>
      <DisplayNo>1112</DisplayNo>
      <DontHide>false</DontHide>
      <IsHideInNotCombat>false</IsHideInNotCombat>
      <ExtendBeyondOriginalRecastTime>false</ExtendBeyondOriginalRecastTime>
      <HideSpellName>true</HideSpellName>
      <HideCounter>false</HideCounter>
      <IsCounterToCenter>false</IsCounterToCenter>
      <IsReverse>true</IsReverse>
      <MatchDateTime>0001-01-01T00:00:00</MatchDateTime>
      <UseHotbarRecastTime>false</UseHotbarRecastTime>
      <HotbarName />
      <ReduceIconBrightness>true</ReduceIconBrightness>
      <SpellIcon>3557_バトルリタニー.png</SpellIcon>
      <SpellIconSize>29</SpellIconSize>
      <IsNotResetAtWipeout>false</IsNotResetAtWipeout>
      <TimeupHide>false</TimeupHide>
      <ToInstance>true</ToInstance>
      <UpperLimitOfExtension>0</UpperLimitOfExtension>
      <BlinkTime>0</BlinkTime>
      <BlinkIcon>false</BlinkIcon>
      <BlinkBar>false</BlinkBar>
      <JobFilter />
      <PartyJobFilter>22</PartyJobFilter>
      <PartyCompositionFilter>LightParty,FullPartyT1,FullPartyT2</PartyCompositionFilter>
      <ZoneFilter />
      <TimersMustRunningForStart />
      <TimersMustStoppingForStart />
      <ExpressionFilter>
        <expression />
        <expression />
        <expression />
        <expression />
      </ExpressionFilter>
      <IsSequentialTTS>false</IsSequentialTTS>
      <MatchTextToSpeak />
      <MatchAdvancedConfig>
        <IsEnabled>false</IsEnabled>
        <ToMainDevice>true</ToMainDevice>
        <ToSubDevice>false</ToSubDevice>
        <ToDicordTextChat>false</ToDicordTextChat>
        <Palette>Default</Palette>
      </MatchAdvancedConfig>
      <OverTime>0</OverTime>
      <OverTextToSpeak />
      <OverAdvancedConfig>
        <IsEnabled>false</IsEnabled>
        <ToMainDevice>true</ToMainDevice>
        <ToSubDevice>false</ToSubDevice>
        <ToDicordTextChat>false</ToDicordTextChat>
        <Palette>Default</Palette>
      </OverAdvancedConfig>
      <BeforeTime>0</BeforeTime>
      <BeforeTextToSpeak />
      <BeforeAdvancedConfig>
        <IsEnabled>false</IsEnabled>
        <ToMainDevice>true</ToMainDevice>
        <ToSubDevice>false</ToSubDevice>
        <ToDicordTextChat>false</ToDicordTextChat>
        <Palette>Default</Palette>
      </BeforeAdvancedConfig>
      <TimeupTextToSpeak />
      <TimeupAdvancedConfig>
        <IsEnabled>false</IsEnabled>
        <ToMainDevice>true</ToMainDevice>
        <ToSubDevice>false</ToSubDevice>
        <ToDicordTextChat>false</ToDicordTextChat>
        <Palette>Default</Palette>
      </TimeupAdvancedConfig>
      <MatchSound />
      <OverSound />
      <BeforeSound />
      <TimeupSound />
    </SpellTimer>
    <SpellTimer>
      <SortPriority>0</SortPriority>
      <IsChecked>false</IsChecked>
      <IsExpanded>false</IsExpanded>
      <Enabled>false</Enabled>
      <IsCircleStyle>true</IsCircleStyle>
      <TitleVerticalAlignmentInCircle>Center</TitleVerticalAlignmentInCircle>
      <Left>0</Left>
      <Top>0</Top>
      <ID>22</ID>
      <Guid>1c6fec3a-cc01-40ff-a3ce-52b99d244246</Guid>
      <PanelID>682207e0-c8bb-40ee-9f5a-687041c092fd</PanelID>
      <Panel>シナジースキル効果時間表示</Panel>
      <SpellTitle>バトルボイス：効果</SpellTitle>
      <RegexEnabled>true</RegexEnabled>
      <Keyword>&lt;mex&gt; gains the effect of バトルボイス</Keyword>
      <KeywordForExtend1 />
      <KeywordForExtend2 />
      <RecastTime>180</RecastTime>
      <DelayToShow>0</DelayToShow>
      <RecastTimeExtending1>0</RecastTimeExtending1>
      <RecastTimeExtending2>0</RecastTimeExtending2>
      <RecastTimeExtending3>0</RecastTimeExtending3>
      <OverlapRecastTime>true</OverlapRecastTime>
      <IsNotResetBarOnExtended>false</IsNotResetBarOnExtended>
      <ProgressBarVisible>true</ProgressBarVisible>
      <Font FontFamily="Impact" Size="13" Stretch="Condensed" Style="Normal" Weight="Normal" />
      <FontColor>#FFFFFF</FontColor>
      <FontOutlineColor>#0000FF</FontOutlineColor>
      <WarningTime>3</WarningTime>
      <ChangeFontColorsWhenWarning>true</ChangeFontColorsWhenWarning>
      <WarningFontColor>Transparent</WarningFontColor>
      <WarningFontOutlineColor>Transparent</WarningFontOutlineColor>
      <ChangeFontColorWhenContainsMe>false</ChangeFontColorWhenContainsMe>
      <BarWidth>35</BarWidth>
      <BarHeight>3</BarHeight>
      <BarColor>#FEF263</BarColor>
      <BarOutlineColor>#000000</BarOutlineColor>
      <BarBlurRadius>15</BarBlurRadius>
      <BackgroundColor>#FFFFFF</BackgroundColor>
      <BackgroundAlpha>0</BackgroundAlpha>
      <DisplayNo>1113</DisplayNo>
      <DontHide>false</DontHide>
      <IsHideInNotCombat>false</IsHideInNotCombat>
      <ExtendBeyondOriginalRecastTime>false</ExtendBeyondOriginalRecastTime>
      <HideSpellName>true</HideSpellName>
      <HideCounter>false</HideCounter>
      <IsCounterToCenter>false</IsCounterToCenter>
      <IsReverse>true</IsReverse>
      <MatchDateTime>0001-01-01T00:00:00</MatchDateTime>
      <UseHotbarRecastTime>false</UseHotbarRecastTime>
      <HotbarName />
      <ReduceIconBrightness>true</ReduceIconBrightness>
      <SpellIcon>0118_バトルボイス.png</SpellIcon>
      <SpellIconSize>29</SpellIconSize>
      <IsNotResetAtWipeout>false</IsNotResetAtWipeout>
      <TimeupHide>false</TimeupHide>
      <ToInstance>true</ToInstance>
      <UpperLimitOfExtension>0</UpperLimitOfExtension>
      <BlinkTime>0</BlinkTime>
      <BlinkIcon>false</BlinkIcon>
      <BlinkBar>false</BlinkBar>
      <JobFilter />
      <PartyJobFilter>23</PartyJobFilter>
      <PartyCompositionFilter>LightParty,FullPartyT1,FullPartyT2</PartyCompositionFilter>
      <ZoneFilter />
      <TimersMustRunningForStart />
      <TimersMustStoppingForStart />
      <ExpressionFilter>
        <expression />
        <expression />
        <expression />
        <expression />
      </ExpressionFilter>
      <IsSequentialTTS>false</IsSequentialTTS>
      <MatchTextToSpeak />
      <MatchAdvancedConfig>
        <IsEnabled>false</IsEnabled>
        <ToMainDevice>true</ToMainDevice>
        <ToSubDevice>false</ToSubDevice>
        <ToDicordTextChat>false</ToDicordTextChat>
        <Palette>Default</Palette>
      </MatchAdvancedConfig>
      <OverTime>0</OverTime>
      <OverTextToSpeak />
      <OverAdvancedConfig>
        <IsEnabled>false</IsEnabled>
        <ToMainDevice>true</ToMainDevice>
        <ToSubDevice>false</ToSubDevice>
        <ToDicordTextChat>false</ToDicordTextChat>
        <Palette>Default</Palette>
      </OverAdvancedConfig>
      <BeforeTime>0</BeforeTime>
      <BeforeTextToSpeak />
      <BeforeAdvancedConfig>
        <IsEnabled>false</IsEnabled>
        <ToMainDevice>true</ToMainDevice>
        <ToSubDevice>false</ToSubDevice>
        <ToDicordTextChat>false</ToDicordTextChat>
        <Palette>Default</Palette>
      </BeforeAdvancedConfig>
      <TimeupTextToSpeak />
      <TimeupAdvancedConfig>
        <IsEnabled>false</IsEnabled>
        <ToMainDevice>true</ToMainDevice>
        <ToSubDevice>false</ToSubDevice>
        <ToDicordTextChat>false</ToDicordTextChat>
        <Palette>Default</Palette>
      </TimeupAdvancedConfig>
      <MatchSound />
      <OverSound />
      <BeforeSound />
      <TimeupSound />
    </SpellTimer>
    <SpellTimer>
      <SortPriority>0</SortPriority>
      <IsChecked>false</IsChecked>
      <IsExpanded>false</IsExpanded>
      <Enabled>false</Enabled>
      <IsCircleStyle>true</IsCircleStyle>
      <TitleVerticalAlignmentInCircle>Center</TitleVerticalAlignmentInCircle>
      <Left>0</Left>
      <Top>0</Top>
      <ID>18</ID>
      <Guid>67e016e2-4d6b-4000-a492-db87409460a7</Guid>
      <PanelID>682207e0-c8bb-40ee-9f5a-687041c092fd</PanelID>
      <Panel>シナジースキル効果時間表示</Panel>
      <SpellTitle>連環計：効果</SpellTitle>
      <RegexEnabled>true</RegexEnabled>
      <Keyword>gains the effect of 連環計 from &lt;SCH&gt;</Keyword>
      <KeywordForExtend1 />
      <KeywordForExtend2 />
      <RecastTime>120</RecastTime>
      <DelayToShow>0</DelayToShow>
      <RecastTimeExtending1>0</RecastTimeExtending1>
      <RecastTimeExtending2>0</RecastTimeExtending2>
      <RecastTimeExtending3>0</RecastTimeExtending3>
      <OverlapRecastTime>true</OverlapRecastTime>
      <IsNotResetBarOnExtended>false</IsNotResetBarOnExtended>
      <ProgressBarVisible>true</ProgressBarVisible>
      <Font FontFamily="Impact" Size="13" Stretch="Condensed" Style="Normal" Weight="Normal" />
      <FontColor>#FFFFFF</FontColor>
      <FontOutlineColor>#0000FF</FontOutlineColor>
      <WarningTime>3</WarningTime>
      <ChangeFontColorsWhenWarning>true</ChangeFontColorsWhenWarning>
      <WarningFontColor>Transparent</WarningFontColor>
      <WarningFontOutlineColor>Transparent</WarningFontOutlineColor>
      <ChangeFontColorWhenContainsMe>false</ChangeFontColorWhenContainsMe>
      <BarWidth>35</BarWidth>
      <BarHeight>3</BarHeight>
      <BarColor>#FEF263</BarColor>
      <BarOutlineColor>#000000</BarOutlineColor>
      <BarBlurRadius>15</BarBlurRadius>
      <BackgroundColor>#FFFFFF</BackgroundColor>
      <BackgroundAlpha>0</BackgroundAlpha>
      <DisplayNo>1114</DisplayNo>
      <DontHide>false</DontHide>
      <IsHideInNotCombat>false</IsHideInNotCombat>
      <ExtendBeyondOriginalRecastTime>false</ExtendBeyondOriginalRecastTime>
      <HideSpellName>true</HideSpellName>
      <HideCounter>false</HideCounter>
      <IsCounterToCenter>false</IsCounterToCenter>
      <IsReverse>true</IsReverse>
      <MatchDateTime>0001-01-01T00:00:00</MatchDateTime>
      <UseHotbarRecastTime>false</UseHotbarRecastTime>
      <HotbarName />
      <ReduceIconBrightness>true</ReduceIconBrightness>
      <SpellIcon>7436_連環計.png</SpellIcon>
      <SpellIconSize>29</SpellIconSize>
      <IsNotResetAtWipeout>false</IsNotResetAtWipeout>
      <TimeupHide>false</TimeupHide>
      <ToInstance>true</ToInstance>
      <UpperLimitOfExtension>0</UpperLimitOfExtension>
      <BlinkTime>0</BlinkTime>
      <BlinkIcon>false</BlinkIcon>
      <BlinkBar>false</BlinkBar>
      <JobFilter />
      <PartyJobFilter>28</PartyJobFilter>
      <PartyCompositionFilter>LightParty,FullPartyT1,FullPartyT2</PartyCompositionFilter>
      <ZoneFilter />
      <TimersMustRunningForStart />
      <TimersMustStoppingForStart />
      <ExpressionFilter>
        <expression />
        <expression />
        <expression />
        <expression />
      </ExpressionFilter>
      <IsSequentialTTS>false</IsSequentialTTS>
      <MatchTextToSpeak />
      <MatchAdvancedConfig>
        <IsEnabled>false</IsEnabled>
        <ToMainDevice>true</ToMainDevice>
        <ToSubDevice>false</ToSubDevice>
        <ToDicordTextChat>false</ToDicordTextChat>
        <Palette>Default</Palette>
      </MatchAdvancedConfig>
      <OverTime>0</OverTime>
      <OverTextToSpeak />
      <OverAdvancedConfig>
        <IsEnabled>false</IsEnabled>
        <ToMainDevice>true</ToMainDevice>
        <ToSubDevice>false</ToSubDevice>
        <ToDicordTextChat>false</ToDicordTextChat>
        <Palette>Default</Palette>
      </OverAdvancedConfig>
      <BeforeTime>0</BeforeTime>
      <BeforeTextToSpeak />
      <BeforeAdvancedConfig>
        <IsEnabled>false</IsEnabled>
        <ToMainDevice>true</ToMainDevice>
        <ToSubDevice>false</ToSubDevice>
        <ToDicordTextChat>false</ToDicordTextChat>
        <Palette>Default</Palette>
      </BeforeAdvancedConfig>
      <TimeupTextToSpeak />
      <TimeupAdvancedConfig>
        <IsEnabled>false</IsEnabled>
        <ToMainDevice>true</ToMainDevice>
        <ToSubDevice>false</ToSubDevice>
        <ToDicordTextChat>false</ToDicordTextChat>
        <Palette>Default</Palette>
      </TimeupAdvancedConfig>
      <MatchSound />
      <OverSound />
      <BeforeSound />
      <TimeupSound />
    </SpellTimer>
  </Spells>
  <Tickers />
</Exports>